{
  "skillTree": [
    [
      {
        "key": "mixu_skill_node_tmb_ramhotep_mount_0",
        "image_path": "mount_skeleton_chariot.png",
        "is_background_skill": false,
        "name": "Skeleton Chariot",
        "description": "The pride of Nehekharan armies, impacting enemy lines with bone-shattering force and grinding the corpses beneath their heavy wheels.",
        "levels": [
          {
            "effects": [
              {
                "icon": "mount.png",
                "priority": 50,
                "is_positive_value_good": true,
                "description": "Mount: Skeleton Chariot",
                "key": "wh2_dlc09_effect_enable_mount_tmb_skeleton_chariot",
                "value": 1
              }
            ],
            "auto_unlock_at_rank": 10
          }
        ],
        "character_skill_key": "mixu_tmb_ramhotep_mount_skeleton_chariot",
        "tier": 0,
        "indent": 0,
        "points_on_creation": 0,
        "required_num_parents": 0,
        "visible_in_ui": true
      },
      {
        "key": "mixu_skill_node_tmb_ramhotep_mount_1",
        "image_path": "mount_necroserpent.png",
        "is_background_skill": false,
        "name": "Emerald Necroserpent",
        "description": "Tougher than normal necroserpents, this Ramhotep's creation is a monstrous mount that shatters bones with every swipe of its tail and sink scimitar-sized fangs deep into soft flesh.",
        "levels": [
          {
            "effects": [
              {
                "icon": "mount.png",
                "priority": 50,
                "is_positive_value_good": true,
                "description": "Mount: Necroserpent",
                "key": "wh2_dlc09_effect_enable_mount_tmb_necroserpent",
                "value": 1
              }
            ],
            "auto_unlock_at_rank": 18
          }
        ],
        "character_skill_key": "mixu_tmb_ramhotep_mount_necroserpent",
        "tier": 1,
        "indent": 0,
        "points_on_creation": 0,
        "required_num_parents": 0,
        "visible_in_ui": true
      },
      {
        "key": "mixu_skill_node_tmb_ramhotep_mount_2",
        "image_path": "mount_warsphinx.png",
        "is_background_skill": false,
        "name": "Khemrian Warsphinx",
        "description": "Giant leonine statues, almost impervious to harm; they wade through foes, crushing them like bothersome insects.",
        "levels": [
          {
            "effects": [
              {
                "icon": "mount.png",
                "priority": 50,
                "is_positive_value_good": true,
                "description": "Mount: Khemrian Warsphinx",
                "key": "wh2_dlc09_effect_enable_mount_tmb_khemrian_warsphinx",
                "value": 1
              }
            ],
            "auto_unlock_at_rank": 30
          }
        ],
        "character_skill_key": "mixu_tmb_ramhotep_mount_warsphinx",
        "tier": 2,
        "indent": 0,
        "points_on_creation": 0,
        "required_num_parents": 0,
        "visible_in_ui": true
      },
      {
        "key": "mixu_skill_node_tmb_ramhotep_misc_0",
        "image_path": "character_ward_save.png",
        "is_background_skill": false,
        "name": "Ceremonial Bandages",
        "description": "Soaked in and toughened by embalming fluid, the cloth bindings used to mummify afford the wearer additional protection from all but a direct hit from mortal projectiles.",
        "levels": [
          {
            "unlocked_at_rank": 8,
            "effects": [
              {
                "icon": "resistance_missile.png",
                "priority": 280,
                "is_positive_value_good": true,
                "description": "Missile resistance: 15%",
                "key": "wh_main_effect_character_stat_missile_resistance",
                "value": 15
              }
            ]
          }
        ],
        "character_skill_key": "wh2_dlc09_skill_tmb_tomb_king_ceremonial_bandages",
        "tier": 3,
        "indent": 0,
        "points_on_creation": 0,
        "required_num_parents": 0,
        "visible_in_ui": true
      },
      {
        "key": "mixu_skill_node_tmb_ramhotep_misc_1",
        "image_path": "character_ward_save.png",
        "is_background_skill": false,
        "name": "Trapped Soul",
        "description": "Souls retrieved from the Netherwold and bound to their controller provide a degree of magical resistance.",
        "levels": [
          {
            "unlocked_at_rank": 12,
            "effects": [
              {
                "icon": "resistance_magic.png",
                "priority": 280,
                "is_positive_value_good": true,
                "description": "Spell resistance: 15%",
                "key": "wh_main_effect_character_stat_magic_resistance",
                "value": 15
              },
              {
                "icon": "attribute_causes_terror.png",
                "priority": 320,
                "is_positive_value_good": true,
                "description": "Attribute: Causes Terror",
                "key": "wh_main_effect_attribute_enable_causes_terror",
                "value": 1
              }
            ]
          }
        ],
        "character_skill_key": "wh2_dlc09_skill_tmb_tomb_king_trapped_soul",
        "tier": 4,
        "indent": 0,
        "points_on_creation": 0,
        "required_num_parents": 0,
        "visible_in_ui": true
      }
    ],
    [
      {
        "key": "mixu_skill_node_tmb_ramhotep_special_0",
        "image_path": "frenzy_character.png",
        "is_background_skill": false,
        "name": "Frantic Fervour",
        "description": "",
        "levels": [
          {
            "unlocked_at_rank": 5,
            "effects": [
              {
                "icon": "item_ability.png",
                "priority": 33,
                "is_positive_value_good": true,
                "description": "Passive ability: \"Frantic Fervour\"",
                "related_abilities": [
                  {
                    "effect": "mixu_tmb_ramhotep_enable_ability_frantic_fervour",
                    "bonus_value_id": "enable",
                    "unit_ability": {
                      "key": "mixu_tmb_ramhotep_ability_frantic_fervour",
                      "icon_name": "wh2_dlc10_quest_passive_primal_rage",
                      "overpower_option": "",
                      "type": {
                        "key": "wh_type_area_of_augments",
                        "icon_path": "icon_spell_area_of_augments.png",
                        "description": "Augment (Area)"
                      },
                      "is_hidden_in_ui": false,
                      "description": "Frantic Fervour",
                      "effect_range": 60,
                      "target_friends": false,
                      "target_enemies": false,
                      "target_ground": false,
                      "target_intercept_range": 0,
                      "target_self": false,
                      "phases": [
                        {
                          "duration": -1,
                          "effect_type": "positive",
                          "is_hidden_in_ui": false,
                          "freeze_recharge": false,
                          "attributes": [
                            {
                              "key": "immune_to_psychology",
                              "description": " Immune to Psychology",
                              "attribute_type": "positive"
                            }
                          ],
                          "stat_effects": [
                            {
                              "value": 1.1,
                              "stat": "stat_charge_bonus",
                              "how": "mult",
                              "description": "x1.1 Charge Bonus",
                              "sort_order": 4,
                              "icon": "icon_stat_charge_bonus.png"
                            },
                            {
                              "value": 8,
                              "stat": "stat_melee_attack",
                              "how": "add",
                              "description": "+8 Melee Attack",
                              "sort_order": 2,
                              "icon": "icon_stat_attack.png"
                            },
                            {
                              "value": 1.1,
                              "stat": "stat_melee_damage_base",
                              "how": "mult",
                              "description": "x1.1 Base Weapon Damage",
                              "sort_order": 0,
                              "icon": "icon_stat_damage_base.png"
                            }
                          ]
                        }
                      ],
                      "target_if": [
                        "Unit is construct"
                      ]
                    }
                  }
                ],
                "key": "mixu_tmb_ramhotep_enable_ability_frantic_fervour",
                "value": 1
              }
            ]
          }
        ],
        "character_skill_key": "mixu_tmb_ramhotep_special_frantic_fervour",
        "tier": 0,
        "indent": 1,
        "points_on_creation": 0,
        "required_num_parents": 0,
        "visible_in_ui": true,
        "right_arrow": true
      },
      {
        "key": "mixu_skill_node_tmb_ramhotep_special_1_1",
        "image_path": "wh2_dlc09_restore.png",
        "is_background_skill": false,
        "name": "Restore",
        "description": "Reaching behind the wall of death to bring back the soul and bind it to you takes skill, but like anything, practice makes perfect!",
        "levels": [
          {
            "effects": [
              {
                "icon": "general_ability.png",
                "priority": 300,
                "is_positive_value_good": true,
                "description": "Ability: \"Restore\"",
                "related_abilities": [
                  {
                    "effect": "wh2_dlc09_effect_ability_enable_restore",
                    "bonus_value_id": "enable",
                    "unit_ability": {
                      "key": "wh2_dlc09_character_abilities_restore",
                      "icon_name": "wh2_dlc09_character_abilities_restore",
                      "overpower_option": "",
                      "type": {
                        "key": "wh_type_regeneration",
                        "icon_path": "icon_spell_regeneration.png",
                        "description": "Regeneration"
                      },
                      "is_hidden_in_ui": false,
                      "description": "Restore",
                      "ui_effects": [
                        {
                          "key": "wh_main_all_replenish",
                          "sort_order": 105,
                          "effect_state": "positive",
                          "description": "Replenishes hit points of combatants"
                        }
                      ],
                      "num_uses": 2,
                      "active_time": 24,
                      "recharge_time": 60,
                      "effect_range": 0,
                      "target_friends": true,
                      "target_enemies": false,
                      "target_ground": false,
                      "target_intercept_range": 100,
                      "target_self": false,
                      "phases": [
                        {
                          "duration": 24,
                          "effect_type": "positive",
                          "hp_change_frequency": 1,
                          "heal_amount": 0.008,
                          "is_hidden_in_ui": false,
                          "freeze_recharge": false
                        }
                      ],
                      "target_if": [
                        "Unit is construct"
                      ]
                    }
                  }
                ],
                "key": "wh2_dlc09_effect_ability_enable_restore",
                "value": 1
              }
            ]
          }
        ],
        "character_skill_key": "wh2_dlc09_skill_tmb_necrotect_ability_0",
        "tier": 2,
        "indent": 1,
        "points_on_creation": 0,
        "required_num_parents": 0,
        "visible_in_ui": true,
        "parent_required": [
          "mixu_skill_node_tmb_ramhotep_special_0"
        ],
        "boxed": true
      },
      {
        "key": "mixu_skill_node_tmb_ramhotep_special_1_2",
        "image_path": "wh2_dlc09_stone_shaper.png",
        "is_background_skill": false,
        "name": "Stone Shaper",
        "description": "The strength at the base of the pillar; the venom of the cobra and the asp. ",
        "levels": [
          {
            "effects": [
              {
                "icon": "general_ability.png",
                "priority": 310,
                "is_positive_value_good": true,
                "description": "Passive ability: \"Stone Shaper\"",
                "related_abilities": [
                  {
                    "effect": "wh2_dlc09_effect_ability_enable_stone_shaper",
                    "bonus_value_id": "enable",
                    "unit_ability": {
                      "key": "wh2_dlc09_character_passive_stone_shaper",
                      "icon_name": "wh2_dlc09_character_passive_stone_shaper",
                      "overpower_option": "",
                      "type": {
                        "key": "wh_type_area_of_augments",
                        "icon_path": "icon_spell_area_of_augments.png",
                        "description": "Augment (Area)"
                      },
                      "is_hidden_in_ui": false,
                      "description": "Stone Shaper",
                      "effect_range": 35,
                      "target_friends": false,
                      "target_enemies": false,
                      "target_ground": false,
                      "target_intercept_range": 0,
                      "target_self": false,
                      "phases": [
                        {
                          "duration": -1,
                          "effect_type": "positive",
                          "is_hidden_in_ui": false,
                          "freeze_recharge": false,
                          "stat_effects": [
                            {
                              "value": 15,
                              "stat": "stat_armour",
                              "how": "add",
                              "description": "+15 Armour",
                              "sort_order": 6,
                              "icon": "icon_stat_armour.png"
                            },
                            {
                              "value": 10,
                              "stat": "stat_resistance_missile",
                              "how": "add",
                              "description": "+10 Missile Resistance",
                              "sort_order": 10,
                              "icon": "resistance_missile.png"
                            }
                          ]
                        }
                      ],
                      "target_if": [
                        "Unit is construct"
                      ]
                    }
                  }
                ],
                "key": "wh2_dlc09_effect_ability_enable_stone_shaper",
                "value": 1
              }
            ]
          }
        ],
        "character_skill_key": "wh2_dlc09_skill_tmb_necrotect_ability_1",
        "tier": 3,
        "indent": 1,
        "points_on_creation": 0,
        "required_num_parents": 0,
        "visible_in_ui": true,
        "parent_required": [
          "mixu_skill_node_tmb_ramhotep_special_0"
        ],
        "boxed": true
      },
      {
        "key": "mixu_skill_node_tmb_ramhotep_special_1_3",
        "image_path": "wh2_dlc09_wrath_of_the_creator.png",
        "is_background_skill": false,
        "name": "Wrath of the Creator",
        "description": "Hatred this strong is infectious, contagious, and inescapable.",
        "levels": [
          {
            "effects": [
              {
                "icon": "general_ability.png",
                "priority": 310,
                "is_positive_value_good": true,
                "description": "Passive ability: \"Wrath of the Creator\"",
                "related_abilities": [
                  {
                    "effect": "wh2_dlc09_effect_ability_enable_wrath_of_the_creator",
                    "bonus_value_id": "enable",
                    "unit_ability": {
                      "key": "wh2_dlc09_character_passive_wrath_of_the_creator",
                      "icon_name": "wh2_dlc09_character_passive_wrath_of_the_creator",
                      "overpower_option": "",
                      "type": {
                        "key": "wh_type_area_of_augments",
                        "icon_path": "icon_spell_area_of_augments.png",
                        "description": "Augment (Area)"
                      },
                      "is_hidden_in_ui": false,
                      "description": "Wrath of the Creator",
                      "effect_range": 35,
                      "target_friends": false,
                      "target_enemies": false,
                      "target_ground": false,
                      "target_intercept_range": 0,
                      "target_self": false,
                      "phases": [
                        {
                          "duration": -1,
                          "effect_type": "positive",
                          "is_hidden_in_ui": false,
                          "freeze_recharge": false,
                          "stat_effects": [
                            {
                              "value": 5,
                              "stat": "stat_melee_attack",
                              "how": "add",
                              "description": "+5 Melee Attack",
                              "sort_order": 2,
                              "icon": "icon_stat_attack.png"
                            },
                            {
                              "value": 1.1,
                              "stat": "stat_melee_damage_ap",
                              "how": "mult",
                              "description": "x1.1 Armour-Piercing Weapon Damage",
                              "sort_order": 0,
                              "icon": "modifier_icon_armour_piercing.png"
                            }
                          ]
                        }
                      ],
                      "target_if": [
                        "Unit is construct"
                      ]
                    }
                  }
                ],
                "key": "wh2_dlc09_effect_ability_enable_wrath_of_the_creator",
                "value": 1
              }
            ]
          }
        ],
        "character_skill_key": "wh2_dlc09_skill_tmb_necrotect_ability_2",
        "tier": 4,
        "indent": 1,
        "points_on_creation": 0,
        "required_num_parents": 0,
        "visible_in_ui": true,
        "parent_required": [
          "mixu_skill_node_tmb_ramhotep_special_0"
        ],
        "right_arrow": true,
        "boxed": true
      },
      {
        "key": "mixu_skill_node_tmb_ramhotep_special_2",
        "image_path": "mixu_master_artisan_1.png",
        "is_background_skill": false,
        "name": "Great Artisan",
        "description": "",
        "levels": [
          {
            "effects": [
              {
                "icon": "general_ability.png",
                "priority": 33,
                "is_positive_value_good": true,
                "description": "Army ability: \"Master Artisan: Sepulchral Stalkers\"\n\t(Hero's army)",
                "key": "mixu_tmb_ramhotep_enable_army_ability_sepulchral_stalkers",
                "value": 1
              }
            ]
          }
        ],
        "character_skill_key": "mixu_tmb_ramhotep_special_master_artisan_1",
        "tier": 5,
        "indent": 1,
        "points_on_creation": 0,
        "required_num_parents": 3,
        "visible_in_ui": true,
        "parent_subset_required": [
          "mixu_skill_node_tmb_ramhotep_special_1_1",
          "mixu_skill_node_tmb_ramhotep_special_1_2",
          "mixu_skill_node_tmb_ramhotep_special_1_3"
        ],
        "right_arrow": true
      },
      {
        "key": "mixu_skill_node_tmb_ramhotep_special_3_1",
        "image_path": "character_construction.png",
        "is_background_skill": false,
        "name": "Relentless Builder",
        "description": "His craftsmanship was second to none, and it is said that his statues in the Valley of Kings were so lifelike that it is said that the kings of Nehekhara believed the gods themselves had returned to the mortal world.",
        "levels": [
          {
            "effects": [
              {
                "icon": "construction.png",
                "priority": 33,
                "is_positive_value_good": false,
                "description": "Construction cost: -30% for Income, Growth, Public Order and Landmark buildings",
                "key": "mixu_LL_build_cost_tmb_landmark_basic_infra",
                "value": -30
              },
              {
                "icon": "construction.png",
                "priority": 33,
                "is_positive_value_good": false,
                "description": "Construction time: -50% for Income, Growth, Public Order and Landmark buildings",
                "key": "mixu_LL_build_time_tmb_landmark_basic_infra",
                "value": -50
              }
            ]
          }
        ],
        "character_skill_key": "mixu_tmb_ramhotep_special_relentless_builder",
        "tier": 6,
        "indent": 1,
        "points_on_creation": 0,
        "required_num_parents": 0,
        "visible_in_ui": true,
        "parent_required": [
          "mixu_skill_node_tmb_ramhotep_special_2"
        ],
        "boxed": true
      },
      {
        "key": "mixu_skill_node_tmb_ramhotep_special_3_2",
        "image_path": "mixu_necrotect.png",
        "is_background_skill": false,
        "name": "Tricked by Ramhotep",
        "description": "In ancient Nehekhara, the finest artisans were commissioned to build grand burial tombs and upon completion they were expected to commit ritual suicide. Ramhotep was aghast at the thought, for it would deny the world of the beautiful creations he had yet to make. Thus, Ramhotep would manipulate the more arrogant Necrotects of the age to take his place.",
        "levels": [
          {
            "effects": [
              {
                "icon": "necrotect.png",
                "priority": 33,
                "is_positive_value_good": true,
                "description": "Hero recruit rank: +5 for Necrotects",
                "key": "mixu_LL_recruit_rank_tmb_necrotect",
                "value": 5
              },
              {
                "icon": "necrotect.png",
                "priority": 102,
                "is_positive_value_good": true,
                "description": "Hero capacity: +1 for Necrotects",
                "key": "wh2_dlc09_effect_agent_cap_increase_tmb_necrotect",
                "value": 1
              },
              {
                "icon": "morale.png",
                "priority": 980,
                "is_positive_value_good": true,
                "description": "Leadership: -15 for Necrotect heroes\n\t(Heroes in local province)",
                "key": "mixu_LL_leadership_tmb_necrotect",
                "value": -15
              }
            ]
          }
        ],
        "character_skill_key": "mixu_tmb_ramhotep_special_tricked_by_ramhotep",
        "tier": 7,
        "indent": 1,
        "points_on_creation": 0,
        "required_num_parents": 0,
        "visible_in_ui": true,
        "parent_required": [
          "mixu_skill_node_tmb_ramhotep_special_2"
        ],
        "boxed": true
      },
      {
        "key": "mixu_skill_node_tmb_ramhotep_special_3_3",
        "image_path": "mixu_statue.png",
        "is_background_skill": false,
        "name": "The Visionary",
        "description": "In life, Ramhotep was consumed by a frenzied compulsion to create and build. No matter how quickly his underlings accomplished their tasks, it was not fast enough for Ramhotep, for there were always more ambitious and grander projects that needed his attention.",
        "levels": [
          {
            "effects": [
              {
                "icon": "weapon_damage.png",
                "priority": 98,
                "is_positive_value_good": true,
                "description": "Weapon damage: +5% for all Construct units\n\t(Hero's army)",
                "key": "mixu_LL_melee_damage_tmb_constructs",
                "value": 5
              },
              {
                "icon": "charge.png",
                "priority": 100,
                "is_positive_value_good": true,
                "description": "Charge bonus: +5% for all Construct units\n\t(Hero's army)",
                "key": "mixu_LL_charge_bonus_tmb_constructs",
                "value": 5
              }
            ]
          },
          {
            "effects": [
              {
                "icon": "weapon_damage.png",
                "priority": 98,
                "is_positive_value_good": true,
                "description": "Weapon damage: +12% for all Construct units\n\t(Hero's army)",
                "key": "mixu_LL_melee_damage_tmb_constructs",
                "value": 12
              },
              {
                "icon": "charge.png",
                "priority": 100,
                "is_positive_value_good": true,
                "description": "Charge bonus: +10% for all Construct units\n\t(Hero's army)",
                "key": "mixu_LL_charge_bonus_tmb_constructs",
                "value": 10
              }
            ]
          }
        ],
        "character_skill_key": "mixu_tmb_ramhotep_special_the_visionary",
        "tier": 8,
        "indent": 1,
        "points_on_creation": 0,
        "required_num_parents": 0,
        "visible_in_ui": true,
        "parent_required": [
          "mixu_skill_node_tmb_ramhotep_special_2"
        ],
        "boxed": true
      },
      {
        "key": "mixu_skill_node_tmb_ramhotep_special_3_4",
        "image_path": "wh2_dlc11_blackmail.png",
        "is_background_skill": false,
        "name": "Ramhotep's Revenge",
        "description": "Upon awakening from his death sleep, Ramhotep was horrified, and he set about excavating and restoring his marvels at once. Ramhotep's skill in undeath is as skilled as it was in life, and the statues that receive his attention are restored to their former majesty, striding into battle as if they were carved only yesterday.",
        "levels": [
          {
            "effects": [
              {
                "icon": "replenishment.png",
                "priority": 101,
                "is_positive_value_good": true,
                "description": "Casualty replenishment rate: +5% for Construct units\n\t(Hero's army)",
                "key": "wh2_dlc09_effect_replenishment_tmb_structures",
                "value": 5
              },
              {
                "icon": "melee_character.png",
                "priority": 130,
                "is_positive_value_good": true,
                "description": "Melee attack: +5",
                "key": "wh_main_effect_character_stat_melee_attack",
                "value": 5
              },
              {
                "icon": "weapon_damage_character.png",
                "priority": 161,
                "is_positive_value_good": true,
                "description": "Weapon strength: +5% when fighting against Greenskins, Skaven, Dark Elves, Beastmen, Warriors of Chaos, Daemons of Chaos and Norsca",
                "key": "wh2_main_effect_character_stat_weapon_strength_vs_forces_of_destruction",
                "value": 5
              }
            ]
          },
          {
            "effects": [
              {
                "icon": "replenishment.png",
                "priority": 101,
                "is_positive_value_good": true,
                "description": "Casualty replenishment rate: +10% for Construct units\n\t(Hero's army)",
                "key": "wh2_dlc09_effect_replenishment_tmb_structures",
                "value": 10
              },
              {
                "icon": "melee_character.png",
                "priority": 130,
                "is_positive_value_good": true,
                "description": "Melee attack: +10",
                "key": "wh_main_effect_character_stat_melee_attack",
                "value": 10
              },
              {
                "icon": "weapon_damage_character.png",
                "priority": 161,
                "is_positive_value_good": true,
                "description": "Weapon strength: +15% when fighting against Greenskins, Skaven, Dark Elves, Beastmen, Warriors of Chaos, Daemons of Chaos and Norsca",
                "key": "wh2_main_effect_character_stat_weapon_strength_vs_forces_of_destruction",
                "value": 15
              }
            ]
          }
        ],
        "character_skill_key": "mixu_tmb_ramhotep_special_ramhoteps_revenge",
        "tier": 9,
        "indent": 1,
        "points_on_creation": 0,
        "required_num_parents": 0,
        "visible_in_ui": true,
        "parent_required": [
          "mixu_skill_node_tmb_ramhotep_special_2"
        ],
        "right_arrow": true,
        "boxed": true
      },
      {
        "key": "mixu_skill_node_tmb_ramhotep_special_4",
        "image_path": "mixu_master_artisan_2.png",
        "is_background_skill": false,
        "name": "Master Artisan",
        "description": "",
        "levels": [
          {
            "effects": [
              {
                "icon": "general_ability.png",
                "priority": 33,
                "is_positive_value_good": true,
                "description": "Army ability: \"Master Artisan: Tomb Scorpion\"\n\t(Hero's army)",
                "key": "mixu_tmb_ramhotep_enable_army_ability_tomb_scorpion",
                "value": 1
              }
            ]
          }
        ],
        "character_skill_key": "mixu_tmb_ramhotep_special_master_artisan_2",
        "tier": 10,
        "indent": 1,
        "points_on_creation": 0,
        "required_num_parents": 4,
        "visible_in_ui": true,
        "parent_subset_required": [
          "mixu_skill_node_tmb_ramhotep_special_3_1",
          "mixu_skill_node_tmb_ramhotep_special_3_2",
          "mixu_skill_node_tmb_ramhotep_special_3_3",
          "mixu_skill_node_tmb_ramhotep_special_3_4"
        ]
      }
    ],
    [
      {
        "key": "mixu_skill_node_tmb_ramhotep_constructs_0",
        "image_path": "character_replenishment.png",
        "is_background_skill": false,
        "name": "Inscription of Repair",
        "description": "This intricate hieroglyphic engraving aids the Necrotect's drive to restore his Tomb King's monuments to their former glory.",
        "levels": [
          {
            "unlocked_at_rank": 10,
            "effects": [
              {
                "icon": "replenishment.png",
                "priority": 101,
                "is_positive_value_good": true,
                "description": "Casualty replenishment rate: +8% for Construct units\n\t(Hero's army)",
                "key": "wh2_dlc09_effect_replenishment_tmb_structures",
                "value": 8
              }
            ]
          }
        ],
        "character_skill_key": "wh2_dlc09_skill_tmb_necrotect_inscription_of_repair",
        "tier": 0,
        "indent": 2,
        "points_on_creation": 0,
        "required_num_parents": 0,
        "visible_in_ui": true,
        "right_arrow": true
      },
      {
        "key": "mixu_skill_node_tmb_ramhotep_constructs_1_1",
        "image_path": "wh2_dlc09_geheb.png",
        "is_background_skill": false,
        "name": "Emerald Sentinels of Lybaras",
        "description": "\"They stand staring into the sun for enternity, the physical embodiedment of the everlasting gods. Terrible ye who looked into their divine forms! \"",
        "levels": [
          {
            "effects": [
              {
                "icon": "unit_capacity.png",
                "priority": 1,
                "is_positive_value_good": true,
                "description": "Unit capacity: +1\n\tUshabti\n\tUshabti (Great Bow)",
                "key": "wh2_dlc09_effect_unit_cap_tmb_jackal",
                "value": 1
              },
              {
                "icon": "general_ability.png",
                "priority": 33,
                "is_positive_value_good": true,
                "description": "Grants the Emerald Sentinels of Lybaras follower to your faction",
                "key": "mixu_tmb_ramhotep_enable_construct_emerald_sentinels_of_lybaras",
                "value": 1
              }
            ]
          }
        ],
        "character_skill_key": "mixu_tmb_ramhotep_constructs_emerald_sentinels_of_lybaras",
        "tier": 1,
        "indent": 2,
        "points_on_creation": 0,
        "required_num_parents": 0,
        "visible_in_ui": true,
        "parent_required": [
          "mixu_skill_node_tmb_ramhotep_constructs_0"
        ],
        "boxed": true
      },
      {
        "key": "mixu_skill_node_tmb_ramhotep_constructs_1_2",
        "image_path": "wh2_dlc09_the_scorpions_sting.png",
        "is_background_skill": false,
        "name": "Underworld Deathwatch",
        "description": "\"Beware the guardians of the Underworld who stalk among us!\"",
        "levels": [
          {
            "effects": [
              {
                "icon": "unit_capacity.png",
                "priority": 1,
                "is_positive_value_good": true,
                "description": "Unit capacity: +1\n\tTomb Scorpion",
                "key": "wh2_dlc09_effect_unit_cap_tmb_mon_tomb_scorpion_0",
                "value": 1
              },
              {
                "icon": "general_ability.png",
                "priority": 33,
                "is_positive_value_good": true,
                "description": "Grants the Underworld Deathwatch follower to your faction",
                "key": "mixu_tmb_ramhotep_enable_construct_underworld_deathwatch",
                "value": 1
              }
            ]
          }
        ],
        "character_skill_key": "mixu_tmb_ramhotep_constructs_underworld_deathwatch",
        "tier": 2,
        "indent": 2,
        "points_on_creation": 0,
        "required_num_parents": 0,
        "visible_in_ui": true,
        "parent_required": [
          "mixu_skill_node_tmb_ramhotep_constructs_0"
        ],
        "boxed": true
      },
      {
        "key": "mixu_skill_node_tmb_ramhotep_constructs_1_3",
        "image_path": "wh2_dlc09_guardian_garagantuan.png",
        "is_background_skill": false,
        "name": "Those That Stalk Beneath the Sand",
        "description": "When the trap is sprung, several horrifying, snake-like forms burst from the ground to surround their prey. The Sepulchral Stalkers impale their foes on ornate staves before they even realize they are under attack.",
        "levels": [
          {
            "effects": [
              {
                "icon": "unit_capacity.png",
                "priority": 1,
                "is_positive_value_good": true,
                "description": "Unit capacity: +1\n\tSepulchral Stalkers",
                "key": "wh2_dlc09_effect_unit_cap_tmb_mon_sepulchral_stalkers_0",
                "value": 1
              },
              {
                "icon": "general_ability.png",
                "priority": 33,
                "is_positive_value_good": true,
                "description": "Grants the Those That Stalk Beneath the Sand follower to your faction",
                "key": "mixu_tmb_ramhotep_enable_construct_the_sand_snakes",
                "value": 1
              }
            ]
          }
        ],
        "character_skill_key": "mixu_tmb_ramhotep_constructs_the_sand_snakes",
        "tier": 3,
        "indent": 2,
        "points_on_creation": 0,
        "required_num_parents": 0,
        "visible_in_ui": true,
        "parent_required": [
          "mixu_skill_node_tmb_ramhotep_constructs_0"
        ],
        "boxed": true
      },
      {
        "key": "mixu_skill_node_tmb_ramhotep_constructs_1_4",
        "image_path": "wh2_dlc09_asaph.png",
        "is_background_skill": false,
        "name": "Knights of Asaph's Temple",
        "description": "Powerful, elite warriors who ride atop giant snake-shaped statues given to them as a reward for their prowess and utter dedication to their sovereign lord.",
        "levels": [
          {
            "effects": [
              {
                "icon": "unit_capacity.png",
                "priority": 1,
                "is_positive_value_good": true,
                "description": "Unit capacity: +1\n\tNecropolis Knights",
                "key": "wh2_dlc09_effect_unit_cap_tmb_cav_necropolis_knights_0",
                "value": 1
              },
              {
                "icon": "unit_capacity.png",
                "priority": 1,
                "is_positive_value_good": true,
                "description": "Unit capacity: +1\n\tNecropolis Knights (Halberds)",
                "key": "wh2_dlc09_effect_unit_cap_tmb_cav_necropolis_knights_1",
                "value": 1
              },
              {
                "icon": "general_ability.png",
                "priority": 33,
                "is_positive_value_good": true,
                "description": "Grants the Knights of Asaph's Temple follower to your faction",
                "key": "mixu_tmb_ramhotep_enable_construct_knights_of_asaphs_temple",
                "value": 1
              }
            ]
          }
        ],
        "character_skill_key": "mixu_tmb_ramhotep_constructs_knights_of_asaphs_temple",
        "tier": 4,
        "indent": 2,
        "points_on_creation": 0,
        "required_num_parents": 0,
        "visible_in_ui": true,
        "parent_required": [
          "mixu_skill_node_tmb_ramhotep_constructs_0"
        ],
        "boxed": true
      },
      {
        "key": "mixu_skill_node_tmb_ramhotep_constructs_1_5",
        "image_path": "wh2_dlc09_statuesque_sentinels.png",
        "is_background_skill": false,
        "name": "The Skull Guardians",
        "description": "\"That which was stone, arise! Bone and bronze and leather and tar, creature of power awake and visit destruction on the enemies of Khemri!\"",
        "levels": [
          {
            "effects": [
              {
                "icon": "unit_capacity.png",
                "priority": 1,
                "is_positive_value_good": true,
                "description": "Unit capacity: +1\n\tBone Giant",
                "key": "wh2_dlc09_effect_unit_cap_tmb_mon_bone_giant_0",
                "value": 1
              },
              {
                "icon": "general_ability.png",
                "priority": 33,
                "is_positive_value_good": true,
                "description": "Grants the The Skull Guardians follower to your faction",
                "key": "mixu_tmb_ramhotep_enable_construct_the_skull_guardians",
                "value": 1
              }
            ]
          }
        ],
        "character_skill_key": "mixu_tmb_ramhotep_constructs_the_skull_guardians",
        "tier": 5,
        "indent": 2,
        "points_on_creation": 0,
        "required_num_parents": 0,
        "visible_in_ui": true,
        "parent_required": [
          "mixu_skill_node_tmb_ramhotep_constructs_0"
        ],
        "right_arrow": true,
        "boxed": true
      },
      {
        "key": "mixu_skill_node_tmb_ramhotep_constructs_2",
        "image_path": "character_construction.png",
        "is_background_skill": false,
        "name": "Master Builder",
        "description": "The master of the necrotectural art understands all aspects of the construction process; inspiration, labour, time and cost are all within his Undead grasp.",
        "levels": [
          {
            "unlocked_at_rank": 10,
            "effects": [
              {
                "icon": "treasury.png",
                "priority": 101,
                "is_positive_value_good": false,
                "description": "Construction cost: -10% for all buildings\n\t(local province)",
                "key": "wh_main_effect_building_construction_cost_mod",
                "value": -10
              },
              {
                "icon": "construction.png",
                "priority": 102,
                "is_positive_value_good": false,
                "description": "Construction time: -1 for Province Capital/Settlement buildings\n\t(local province)",
                "key": "wh_main_effect_building_construction_time_mod_settlement",
                "value": -1
              }
            ]
          }
        ],
        "character_skill_key": "wh2_dlc09_skill_tmb_necrotect_master_constructor",
        "tier": 6,
        "indent": 2,
        "points_on_creation": 0,
        "required_num_parents": 1,
        "visible_in_ui": true,
        "parent_subset_required": [
          "mixu_skill_node_tmb_ramhotep_constructs_1_1",
          "mixu_skill_node_tmb_ramhotep_constructs_1_2",
          "mixu_skill_node_tmb_ramhotep_constructs_1_3",
          "mixu_skill_node_tmb_ramhotep_constructs_1_4",
          "mixu_skill_node_tmb_ramhotep_constructs_1_5"
        ],
        "right_arrow": true
      },
      {
        "key": "mixu_skill_node_tmb_ramhotep_constructs_3_1",
        "image_path": "wh2_dlc09_sculptor_hierotitan.png",
        "is_background_skill": false,
        "name": "Master Hierotitan Sculptor",
        "description": "No expense was spared in sculpting a Hierotitan - the greatest and most talented of Necrotects were contracted to work on the blessed stone that would form these gigantic statues.",
        "levels": [
          {
            "unlocked_at_rank": 14,
            "effects": [
              {
                "icon": "unit_capacity.png",
                "priority": 1,
                "is_positive_value_good": true,
                "description": "Unit capacity: +1\n\tHierotitan",
                "key": "wh2_dlc09_effect_unit_cap_tmb_mon_heirotitan_0",
                "value": 1
              }
            ],
            "blocks_character_skill_key": [
              "wh2_dlc09_skill_tmb_necrotect_master_necrosphinx",
              "wh2_dlc09_skill_tmb_necrotect_master_warsphinx"
            ]
          }
        ],
        "character_skill_key": "wh2_dlc09_skill_tmb_necrotect_master_heirotitan",
        "tier": 7,
        "indent": 2,
        "points_on_creation": 0,
        "required_num_parents": 0,
        "visible_in_ui": true,
        "parent_required": [
          "mixu_skill_node_tmb_ramhotep_constructs_2"
        ],
        "boxed": true
      },
      {
        "key": "mixu_skill_node_tmb_ramhotep_constructs_3_2",
        "image_path": "wh2_dlc09_sculptor_necrosphinx.png",
        "is_background_skill": false,
        "name": "Master Necrosphinx Sculptor",
        "description": "To carve a Necrosphinx is to manifest the greatest and most destructive creature of the underworld. Not all Necrotects were adept at bringing such constructions to Unlife - only the most gifted of their trade even dare.",
        "levels": [
          {
            "unlocked_at_rank": 14,
            "effects": [
              {
                "icon": "unit_capacity.png",
                "priority": 1,
                "is_positive_value_good": true,
                "description": "Unit capacity: +1\n\tNecrosphinx",
                "key": "wh2_dlc09_effect_unit_cap_tmb_mon_necrosphinx_0",
                "value": 1
              }
            ],
            "blocks_character_skill_key": [
              "wh2_dlc09_skill_tmb_necrotect_master_heirotitan",
              "wh2_dlc09_skill_tmb_necrotect_master_warsphinx"
            ]
          }
        ],
        "character_skill_key": "wh2_dlc09_skill_tmb_necrotect_master_necrosphinx",
        "tier": 8,
        "indent": 2,
        "points_on_creation": 0,
        "required_num_parents": 0,
        "visible_in_ui": true,
        "parent_required": [
          "mixu_skill_node_tmb_ramhotep_constructs_2"
        ],
        "boxed": true
      },
      {
        "key": "mixu_skill_node_tmb_ramhotep_constructs_3_3",
        "image_path": "wh2_dlc09_sculptor_warsphinx.png",
        "is_background_skill": false,
        "name": "Master Warsphinx Sculptor",
        "description": "The leonine statues, known as Warsphinxes, were first constructed in Khemri; and so it is Necrotects who hail from the first city are the greatest carvers of these magnificent and deadly stone beasts.",
        "levels": [
          {
            "unlocked_at_rank": 14,
            "effects": [
              {
                "icon": "unit_capacity.png",
                "priority": 1,
                "is_positive_value_good": true,
                "description": "Unit capacity: +1\n\tKhemrian Warsphinx",
                "key": "wh2_dlc09_effect_unit_cap_tmb_veh_khemrian_warsphinx_0",
                "value": 1
              }
            ],
            "blocks_character_skill_key": [
              "wh2_dlc09_skill_tmb_necrotect_master_heirotitan",
              "wh2_dlc09_skill_tmb_necrotect_master_necrosphinx"
            ]
          }
        ],
        "character_skill_key": "wh2_dlc09_skill_tmb_necrotect_master_warsphinx",
        "tier": 9,
        "indent": 2,
        "points_on_creation": 0,
        "required_num_parents": 0,
        "visible_in_ui": true,
        "parent_required": [
          "mixu_skill_node_tmb_ramhotep_constructs_2"
        ],
        "boxed": true
      }
    ],
    [
      {
        "key": "mixu_skill_node_tmb_ramhotep_personal_0",
        "image_path": "character_morale.png",
        "is_background_skill": false,
        "name": "Indomitable Will",
        "description": "It is not possible to defeat such unshakeable spirit once its owner's mind is made up.",
        "levels": [
          {
            "effects": [
              {
                "icon": "morale_character.png",
                "priority": 110,
                "is_positive_value_good": true,
                "description": "Leadership: +4",
                "key": "wh_main_effect_character_stat_leadership",
                "value": 4
              },
              {
                "icon": "charge_character.png",
                "priority": 200,
                "is_positive_value_good": true,
                "description": "Charge bonus: +5",
                "key": "wh_main_effect_character_stat_charge_bonus_add",
                "value": 5
              }
            ]
          }
        ],
        "character_skill_key": "wh2_dlc09_skill_tmb_personal_base",
        "tier": 0,
        "indent": 3,
        "points_on_creation": 0,
        "required_num_parents": 0,
        "visible_in_ui": true,
        "right_arrow": true
      },
      {
        "key": "mixu_skill_node_tmb_ramhotep_personal_1",
        "image_path": "character_damage.png",
        "is_background_skill": false,
        "name": "Conqueror",
        "description": "Kill many and you *are* a conqueror; godhood is then but a protracted slaughter away...",
        "levels": [
          {
            "effects": [
              {
                "icon": "melee_character.png",
                "priority": 130,
                "is_positive_value_good": true,
                "description": "Melee attack: +4",
                "key": "wh_main_effect_character_stat_melee_attack",
                "value": 4
              },
              {
                "icon": "weapon_damage_character.png",
                "priority": 160,
                "is_positive_value_good": true,
                "description": "Weapon strength: +5%",
                "key": "wh_main_effect_character_stat_weapon_strength",
                "value": 5
              }
            ]
          },
          {
            "effects": [
              {
                "icon": "melee_character.png",
                "priority": 130,
                "is_positive_value_good": true,
                "description": "Melee attack: +8",
                "key": "wh_main_effect_character_stat_melee_attack",
                "value": 8
              },
              {
                "icon": "weapon_damage_character.png",
                "priority": 160,
                "is_positive_value_good": true,
                "description": "Weapon strength: +10%",
                "key": "wh_main_effect_character_stat_weapon_strength",
                "value": 10
              }
            ]
          }
        ],
        "character_skill_key": "wh2_dlc09_skill_tmb_personal_conqueror",
        "tier": 1,
        "indent": 3,
        "points_on_creation": 0,
        "required_num_parents": 0,
        "visible_in_ui": true,
        "parent_required": [
          "mixu_skill_node_tmb_ramhotep_personal_0"
        ],
        "boxed": true
      },
      {
        "key": "mixu_skill_node_tmb_ramhotep_personal_2",
        "image_path": "character_attack.png",
        "is_background_skill": false,
        "name": "Blade Master",
        "description": "This warrior is one with their blade; it is an extension of their will, making them a worthy foe in combat.",
        "levels": [
          {
            "effects": [
              {
                "icon": "melee_character.png",
                "priority": 130,
                "is_positive_value_good": true,
                "description": "Melee attack: +6",
                "key": "wh_main_effect_character_stat_melee_attack",
                "value": 6
              }
            ]
          },
          {
            "effects": [
              {
                "icon": "melee_character.png",
                "priority": 130,
                "is_positive_value_good": true,
                "description": "Melee attack: +12",
                "key": "wh_main_effect_character_stat_melee_attack",
                "value": 12
              }
            ]
          }
        ],
        "character_skill_key": "wh2_dlc11_skill_all_lord_self_blade_master",
        "tier": 2,
        "indent": 3,
        "points_on_creation": 0,
        "required_num_parents": 0,
        "visible_in_ui": true,
        "parent_required": [
          "mixu_skill_node_tmb_ramhotep_personal_0"
        ],
        "boxed": true
      },
      {
        "key": "mixu_skill_node_tmb_ramhotep_personal_3",
        "image_path": "character_defence.png",
        "is_background_skill": false,
        "name": "Hard to Hit",
        "description": "Hand-to-hand combat is a lethal match of cut and thrust. However, its not all about offensive strikes; parries and other defensive moves can also win the day.",
        "levels": [
          {
            "effects": [
              {
                "icon": "defence_character.png",
                "priority": 150,
                "is_positive_value_good": true,
                "description": "Melee defence: +6",
                "key": "wh_main_effect_character_stat_melee_defence",
                "value": 6
              }
            ]
          },
          {
            "effects": [
              {
                "icon": "defence_character.png",
                "priority": 150,
                "is_positive_value_good": true,
                "description": "Melee defence: +12",
                "key": "wh_main_effect_character_stat_melee_defence",
                "value": 12
              }
            ]
          }
        ],
        "character_skill_key": "wh2_dlc11_skill_all_lord_self_hard_to_hit",
        "tier": 3,
        "indent": 3,
        "points_on_creation": 0,
        "required_num_parents": 0,
        "visible_in_ui": true,
        "parent_required": [
          "mixu_skill_node_tmb_ramhotep_personal_0"
        ],
        "boxed": true
      },
      {
        "key": "mixu_skill_node_tmb_ramhotep_personal_4",
        "image_path": "character_morale.png",
        "is_background_skill": false,
        "name": "Indomitable",
        "description": "The iron will and indomitable presence of this leader ensures their followers remain steadfast when facing peril.",
        "levels": [
          {
            "effects": [
              {
                "icon": "morale_character.png",
                "priority": 110,
                "is_positive_value_good": true,
                "description": "Leadership: +6",
                "key": "wh_main_effect_character_stat_leadership",
                "value": 6
              }
            ]
          },
          {
            "effects": [
              {
                "icon": "morale_character.png",
                "priority": 110,
                "is_positive_value_good": true,
                "description": "Leadership: +12",
                "key": "wh_main_effect_character_stat_leadership",
                "value": 12
              }
            ]
          }
        ],
        "character_skill_key": "wh2_dlc11_skill_all_lord_self_self_indomitable",
        "tier": 4,
        "indent": 3,
        "points_on_creation": 0,
        "required_num_parents": 0,
        "visible_in_ui": true,
        "parent_required": [
          "mixu_skill_node_tmb_ramhotep_personal_0"
        ],
        "right_arrow": true,
        "boxed": true
      },
      {
        "key": "mixu_skill_node_tmb_ramhotep_personal_5",
        "image_path": "wh2_dlc09_strike_of_tombs.png",
        "is_background_skill": false,
        "name": "Tombstrike",
        "description": "He whose will transcends death can strike out from beyond the grave, to devastating effect.",
        "levels": [
          {
            "effects": [
              {
                "icon": "general_ability.png",
                "priority": 300,
                "is_positive_value_good": true,
                "description": "Ability: \"Tombstrike\"",
                "related_abilities": [
                  {
                    "effect": "wh2_dlc09_effect_ability_enable_tombstrike",
                    "bonus_value_id": "enable",
                    "unit_ability": {
                      "key": "wh2_dlc09_character_abilities_strike_of_tombs",
                      "icon_name": "wh2_dlc09_character_abilities_strike_of_tombs",
                      "overpower_option": "",
                      "type": {
                        "key": "wh_type_augment",
                        "icon_path": "icon_spell_augment.png",
                        "description": "Augment"
                      },
                      "is_hidden_in_ui": false,
                      "description": "Tombstrike",
                      "active_time": 23,
                      "recharge_time": 90,
                      "effect_range": 0,
                      "target_friends": false,
                      "target_enemies": false,
                      "target_ground": false,
                      "target_intercept_range": 0,
                      "target_self": false,
                      "phases": [
                        {
                          "duration": 23,
                          "effect_type": "positive",
                          "is_hidden_in_ui": false,
                          "freeze_recharge": false,
                          "attributes": [
                            {
                              "key": "causes_terror",
                              "description": " Can Cause Terror",
                              "attribute_type": "positive"
                            }
                          ],
                          "stat_effects": [
                            {
                              "value": 24,
                              "stat": "stat_melee_attack",
                              "how": "add",
                              "description": "+24 Melee Attack",
                              "sort_order": 2,
                              "icon": "icon_stat_attack.png"
                            },
                            {
                              "value": 1.3,
                              "stat": "stat_melee_damage_base",
                              "how": "mult",
                              "description": "x1.3 Base Weapon Damage",
                              "sort_order": 0,
                              "icon": "icon_stat_damage_base.png"
                            }
                          ]
                        }
                      ]
                    }
                  }
                ],
                "key": "wh2_dlc09_effect_ability_enable_tombstrike",
                "value": 1
              }
            ]
          }
        ],
        "character_skill_key": "wh2_dlc09_skill_tmb_personal_5",
        "tier": 5,
        "indent": 3,
        "points_on_creation": 0,
        "required_num_parents": 4,
        "visible_in_ui": true,
        "parent_subset_required": [
          "mixu_skill_node_tmb_ramhotep_personal_1",
          "mixu_skill_node_tmb_ramhotep_personal_2",
          "mixu_skill_node_tmb_ramhotep_personal_3",
          "mixu_skill_node_tmb_ramhotep_personal_4"
        ],
        "right_arrow": true
      },
      {
        "key": "mixu_skill_node_tmb_ramhotep_personal_6",
        "image_path": "character_damage.png",
        "is_background_skill": false,
        "name": "Wound-Maker",
        "description": "Such is their power and ferocity, a wound-maker will ravage the foe, cutting and pulverising until there is only one exit - death.",
        "levels": [
          {
            "effects": [
              {
                "icon": "weapon_damage_character.png",
                "priority": 160,
                "is_positive_value_good": true,
                "description": "Weapon strength: +10%",
                "key": "wh_main_effect_character_stat_weapon_strength",
                "value": 10
              }
            ]
          },
          {
            "effects": [
              {
                "icon": "weapon_damage_character.png",
                "priority": 160,
                "is_positive_value_good": true,
                "description": "Weapon strength: +20%",
                "key": "wh_main_effect_character_stat_weapon_strength",
                "value": 20
              }
            ]
          }
        ],
        "character_skill_key": "wh2_dlc11_skill_all_lord_self_wound-maker",
        "tier": 6,
        "indent": 3,
        "points_on_creation": 0,
        "required_num_parents": 0,
        "visible_in_ui": true,
        "parent_required": [
          "mixu_skill_node_tmb_ramhotep_personal_5"
        ],
        "boxed": true
      },
      {
        "key": "mixu_skill_node_tmb_ramhotep_personal_7",
        "image_path": "character_armour.png",
        "is_background_skill": false,
        "name": "Full Plate Armour",
        "description": "Full-Plate armour protects the wearer from head-to-foot. Many such suits are blessed or imbued with arcane abilities.",
        "levels": [
          {
            "effects": [
              {
                "icon": "armour_character.png",
                "priority": 100,
                "is_positive_value_good": true,
                "description": "Armour: +7",
                "key": "wh_main_effect_character_stat_armour",
                "value": 7
              }
            ]
          },
          {
            "effects": [
              {
                "icon": "armour_character.png",
                "priority": 100,
                "is_positive_value_good": true,
                "description": "Armour: +15",
                "key": "wh_main_effect_character_stat_armour",
                "value": 15
              }
            ]
          }
        ],
        "character_skill_key": "wh2_dlc11_skill_all_lord_self_full_plate_armour",
        "tier": 7,
        "indent": 3,
        "points_on_creation": 0,
        "required_num_parents": 0,
        "visible_in_ui": true,
        "parent_required": [
          "mixu_skill_node_tmb_ramhotep_personal_5"
        ],
        "boxed": true
      },
      {
        "key": "mixu_skill_node_tmb_ramhotep_personal_8",
        "image_path": "character_charge.png",
        "is_background_skill": false,
        "name": "Devastating Charge",
        "description": "Some creatures charge home with such fury that the very ground shakes beneath their feet.",
        "levels": [
          {
            "effects": [
              {
                "icon": "charge_character.png",
                "priority": 200,
                "is_positive_value_good": true,
                "description": "Charge bonus: +15",
                "key": "wh_main_effect_character_stat_charge_bonus_add",
                "value": 15
              }
            ]
          },
          {
            "effects": [
              {
                "icon": "charge_character.png",
                "priority": 200,
                "is_positive_value_good": true,
                "description": "Charge bonus: +30",
                "key": "wh_main_effect_character_stat_charge_bonus_add",
                "value": 30
              }
            ]
          }
        ],
        "character_skill_key": "wh2_dlc11_skill_all_lord_self_devastating_charge",
        "tier": 8,
        "indent": 3,
        "points_on_creation": 0,
        "required_num_parents": 0,
        "visible_in_ui": true,
        "parent_required": [
          "mixu_skill_node_tmb_ramhotep_personal_5"
        ],
        "boxed": true
      },
      {
        "key": "mixu_skill_node_tmb_ramhotep_personal_9",
        "image_path": "character_speed.png",
        "is_background_skill": false,
        "name": "Over My Dead Body",
        "description": "Death is not an impedance to the strongest of wills.",
        "levels": [
          {
            "effects": [
              {
                "icon": "battle_movement_character.png",
                "priority": 120,
                "is_positive_value_good": true,
                "description": "Speed: +8%",
                "key": "wh_main_effect_character_stat_speed",
                "value": 8
              }
            ]
          },
          {
            "effects": [
              {
                "icon": "health_character.png",
                "priority": 90,
                "is_positive_value_good": true,
                "description": "Hit points: +6%",
                "key": "wh_main_effect_character_stat_unit_health",
                "value": 6
              },
              {
                "icon": "battle_movement_character.png",
                "priority": 120,
                "is_positive_value_good": true,
                "description": "Speed: +8%",
                "key": "wh_main_effect_character_stat_speed",
                "value": 8
              }
            ]
          }
        ],
        "character_skill_key": "wh2_dlc09_skill_tmb_personal_9",
        "tier": 9,
        "indent": 3,
        "points_on_creation": 0,
        "required_num_parents": 0,
        "visible_in_ui": true,
        "parent_required": [
          "mixu_skill_node_tmb_ramhotep_personal_5"
        ],
        "right_arrow": true,
        "boxed": true
      },
      {
        "key": "mixu_skill_node_tmb_ramhotep_personal_10",
        "image_path": "wh2_dlc09_strike_of_nehekhara.png",
        "is_background_skill": false,
        "name": "Desertstrike",
        "description": "Beware the scorpion's sting, hidden 'neath the desert sands yet always poised to strike.",
        "levels": [
          {
            "effects": [
              {
                "icon": "general_ability.png",
                "priority": 300,
                "is_positive_value_good": true,
                "description": "Ability: \"Desertstrike\"",
                "related_abilities": [
                  {
                    "effect": "wh2_dlc09_effect_ability_enable_desertstrike",
                    "bonus_value_id": "enable",
                    "unit_ability": {
                      "key": "wh2_dlc09_character_abilities_strike_of_nehekhara",
                      "icon_name": "wh2_dlc09_character_abilities_strike_of_nehekhara",
                      "overpower_option": "",
                      "type": {
                        "key": "wh_type_augment",
                        "icon_path": "icon_spell_augment.png",
                        "description": "Augment"
                      },
                      "is_hidden_in_ui": false,
                      "description": "Desertstrike",
                      "active_time": 23,
                      "recharge_time": 120,
                      "effect_range": 0,
                      "target_friends": false,
                      "target_enemies": false,
                      "target_ground": false,
                      "target_intercept_range": 0,
                      "target_self": false,
                      "phases": [
                        {
                          "duration": 23,
                          "effect_type": "positive",
                          "is_hidden_in_ui": false,
                          "freeze_recharge": false,
                          "attributes": [
                            {
                              "key": "causes_terror",
                              "description": " Can Cause Terror",
                              "attribute_type": "positive"
                            }
                          ],
                          "stat_effects": [
                            {
                              "value": 40,
                              "stat": "stat_melee_attack",
                              "how": "add",
                              "description": "+40 Melee Attack",
                              "sort_order": 2,
                              "icon": "icon_stat_attack.png"
                            },
                            {
                              "value": 1.6,
                              "stat": "stat_melee_damage_base",
                              "how": "mult",
                              "description": "x1.6 Base Weapon Damage",
                              "sort_order": 0,
                              "icon": "icon_stat_damage_base.png"
                            }
                          ]
                        }
                      ]
                    }
                  }
                ],
                "key": "wh2_dlc09_effect_ability_enable_desertstrike",
                "value": 1
              },
              {
                "icon": "general_ability.png",
                "priority": 305,
                "is_positive_value_good": true,
                "description": "Replaces: \"Tombstrike\"",
                "key": "wh2_dlc09_effect_ability_disable_tombstrike",
                "value": 1
              }
            ]
          }
        ],
        "character_skill_key": "wh2_dlc09_skill_tmb_personal_10",
        "tier": 10,
        "indent": 3,
        "points_on_creation": 0,
        "required_num_parents": 4,
        "visible_in_ui": true,
        "parent_subset_required": [
          "mixu_skill_node_tmb_ramhotep_personal_6",
          "mixu_skill_node_tmb_ramhotep_personal_7",
          "mixu_skill_node_tmb_ramhotep_personal_8",
          "mixu_skill_node_tmb_ramhotep_personal_9"
        ]
      }
    ],
    [],
    [
      {
        "key": "mixu_skill_node_tmb_ramhotep_campaign_01",
        "image_path": "campaign_movement.png",
        "is_background_skill": false,
        "name": "Increase Mobility",
        "description": "Whether it be training harder, travelling lighter, eating less or sleeping better, there's always a way to draw more from the day.",
        "levels": [
          {
            "effects": [
              {
                "icon": "campaign_movement.png",
                "priority": 7,
                "is_positive_value_good": true,
                "description": "Increase Mobility action: Movement range is increased by an additional 5%",
                "key": "wh2_main_effect_agent_action_assist_army_increase_mobility_buff",
                "value": 5
              }
            ]
          },
          {
            "unlocked_at_rank": 5,
            "effects": [
              {
                "icon": "campaign_movement.png",
                "priority": 7,
                "is_positive_value_good": true,
                "description": "Increase Mobility action: Movement range is increased by an additional 10%",
                "key": "wh2_main_effect_agent_action_assist_army_increase_mobility_buff",
                "value": 10
              }
            ]
          },
          {
            "unlocked_at_rank": 10,
            "effects": [
              {
                "icon": "campaign_movement.png",
                "priority": 7,
                "is_positive_value_good": true,
                "description": "Increase Mobility action: Movement range is increased by an additional 15%",
                "key": "wh2_main_effect_agent_action_assist_army_increase_mobility_buff",
                "value": 15
              }
            ]
          }
        ],
        "character_skill_key": "wh2_main_skill_all_hero_assist_army_increase_mobility",
        "tier": 0,
        "indent": 5,
        "points_on_creation": 0,
        "required_num_parents": 0,
        "visible_in_ui": true
      },
      {
        "key": "mixu_skill_node_tmb_ramhotep_campaign_02",
        "image_path": "campaign_military_spending.png",
        "is_background_skill": false,
        "name": "Boost Income",
        "description": "Such magic-users may be wise and able to offer sage advice, especially if they have scried the region.",
        "levels": [
          {
            "effects": [
              {
                "icon": "income.png",
                "priority": 0,
                "is_positive_value_good": true,
                "description": "Income from all buildings: -2%\n\t(local province)",
                "key": "wh2_main_effect_agent_action_passive_boost_income_effect_negative",
                "value": -2
              },
              {
                "icon": "income.png",
                "priority": 0,
                "is_positive_value_good": true,
                "description": "Income from all buildings: +2%\n\t(local province)",
                "key": "wh2_main_effect_agent_action_passive_boost_income_effect_positive",
                "value": 2
              },
              {
                "icon": "income.png",
                "priority": 8,
                "is_positive_value_good": true,
                "description": "Boost Income action: Income is modified by an additional 2%",
                "key": "wh2_main_effect_agent_action_passive_boost_income_buff",
                "value": 2
              }
            ]
          },
          {
            "unlocked_at_rank": 5,
            "effects": [
              {
                "icon": "income.png",
                "priority": 0,
                "is_positive_value_good": true,
                "description": "Income from all buildings: -4%\n\t(local province)",
                "key": "wh2_main_effect_agent_action_passive_boost_income_effect_negative",
                "value": -4
              },
              {
                "icon": "income.png",
                "priority": 0,
                "is_positive_value_good": true,
                "description": "Income from all buildings: +4%\n\t(local province)",
                "key": "wh2_main_effect_agent_action_passive_boost_income_effect_positive",
                "value": 4
              },
              {
                "icon": "income.png",
                "priority": 8,
                "is_positive_value_good": true,
                "description": "Boost Income action: Income is modified by an additional 4%",
                "key": "wh2_main_effect_agent_action_passive_boost_income_buff",
                "value": 4
              }
            ]
          },
          {
            "unlocked_at_rank": 10,
            "effects": [
              {
                "icon": "income.png",
                "priority": 0,
                "is_positive_value_good": true,
                "description": "Income from all buildings: -6%\n\t(local province)",
                "key": "wh2_main_effect_agent_action_passive_boost_income_effect_negative",
                "value": -6
              },
              {
                "icon": "income.png",
                "priority": 0,
                "is_positive_value_good": true,
                "description": "Income from all buildings: +6%\n\t(local province)",
                "key": "wh2_main_effect_agent_action_passive_boost_income_effect_positive",
                "value": 6
              },
              {
                "icon": "income.png",
                "priority": 8,
                "is_positive_value_good": true,
                "description": "Boost Income action: Income is modified by an additional 6%",
                "key": "wh2_main_effect_agent_action_passive_boost_income_buff",
                "value": 6
              }
            ]
          }
        ],
        "character_skill_key": "wh2_main_skill_all_hero_passive_boost_income",
        "tier": 1,
        "indent": 5,
        "points_on_creation": 0,
        "required_num_parents": 0,
        "visible_in_ui": true
      },
      {
        "key": "mixu_skill_node_tmb_ramhotep_campaign_03",
        "image_path": "campaign_siege_attack.png",
        "is_background_skill": false,
        "name": "Damage Walls",
        "description": "They cannot stop what they cannot see.",
        "levels": [
          {
            "effects": [
              {
                "icon": "siege_attack.png",
                "priority": 9,
                "is_positive_value_good": true,
                "description": "Damage Walls action: 1 additional wall breaches",
                "key": "wh2_main_effect_agent_action_hinder_settlement_damage_walls_buff",
                "value": 1
              }
            ]
          },
          {
            "unlocked_at_rank": 5,
            "effects": [
              {
                "icon": "siege_attack.png",
                "priority": 9,
                "is_positive_value_good": true,
                "description": "Damage Walls action: 2 additional wall breaches",
                "key": "wh2_main_effect_agent_action_hinder_settlement_damage_walls_buff",
                "value": 2
              }
            ]
          },
          {
            "unlocked_at_rank": 10,
            "effects": [
              {
                "icon": "siege_attack.png",
                "priority": 9,
                "is_positive_value_good": true,
                "description": "Damage Walls action: 3 additional wall breaches",
                "key": "wh2_main_effect_agent_action_hinder_settlement_damage_walls_buff",
                "value": 3
              }
            ]
          }
        ],
        "character_skill_key": "wh2_main_skill_all_hero_hinder_settlement_damage_walls",
        "tier": 2,
        "indent": 5,
        "points_on_creation": 0,
        "required_num_parents": 0,
        "visible_in_ui": true
      },
      {
        "key": "mixu_skill_node_tmb_ramhotep_campaign_04",
        "image_path": "campaign_wound_time.png",
        "is_background_skill": false,
        "name": "Wound",
        "description": "Such a champion will not bend or break, but slay in their Lord's name.",
        "levels": [
          {
            "effects": [
              {
                "icon": "wound_time.png",
                "priority": 10,
                "is_positive_value_good": true,
                "description": "Wound action: Additional 5% chance of wounding target",
                "key": "wh2_main_effect_agent_action_hinder_agent_wound_buff",
                "value": 5
              }
            ]
          },
          {
            "unlocked_at_rank": 5,
            "effects": [
              {
                "icon": "wound_time.png",
                "priority": 10,
                "is_positive_value_good": true,
                "description": "Wound action: Additional 12% chance of wounding target",
                "key": "wh2_main_effect_agent_action_hinder_agent_wound_buff",
                "value": 12
              }
            ]
          },
          {
            "unlocked_at_rank": 10,
            "effects": [
              {
                "icon": "wound_time.png",
                "priority": 10,
                "is_positive_value_good": true,
                "description": "Wound action: Additional 21% chance of wounding target",
                "key": "wh2_main_effect_agent_action_hinder_agent_wound_buff",
                "value": 21
              }
            ]
          }
        ],
        "character_skill_key": "wh2_main_skill_all_hero_hinder_agent_wound",
        "tier": 3,
        "indent": 5,
        "points_on_creation": 0,
        "required_num_parents": 0,
        "visible_in_ui": true
      },
      {
        "key": "mixu_skill_node_tmb_ramhotep_campaign_05",
        "image_path": "campaign_movement.png",
        "is_background_skill": false,
        "name": "Block Army",
        "description": "To sow discord and confuse the enemy, sending them down the wrong route or befuddling their senses.",
        "levels": [
          {
            "effects": [
              {
                "icon": "campaign_movement.png",
                "priority": 11,
                "is_positive_value_good": false,
                "description": "Block Army action: Movement range is modified by an additional -3%",
                "key": "wh2_main_effect_agent_action_hinder_army_block_army_buff",
                "value": -3
              }
            ]
          },
          {
            "unlocked_at_rank": 5,
            "effects": [
              {
                "icon": "campaign_movement.png",
                "priority": 11,
                "is_positive_value_good": false,
                "description": "Block Army action: Movement range is modified by an additional -8%",
                "key": "wh2_main_effect_agent_action_hinder_army_block_army_buff",
                "value": -8
              }
            ]
          },
          {
            "unlocked_at_rank": 10,
            "effects": [
              {
                "icon": "campaign_movement.png",
                "priority": 11,
                "is_positive_value_good": false,
                "description": "Block Army action: Movement range is modified by an additional -15%",
                "key": "wh2_main_effect_agent_action_hinder_army_block_army_buff",
                "value": -15
              }
            ]
          }
        ],
        "character_skill_key": "wh2_main_skill_all_hero_hinder_army_block_army",
        "tier": 4,
        "indent": 5,
        "points_on_creation": 0,
        "required_num_parents": 0,
        "visible_in_ui": true
      },
      {
        "key": "mixu_skill_node_tmb_ramhotep_campaign_06",
        "image_path": "campaign_military_spending.png",
        "is_background_skill": false,
        "name": "Specialist",
        "description": "An expert in their craft, this Hero knows all the mistakes that can be made and how to best avoid making them.",
        "levels": [
          {
            "effects": [
              {
                "icon": "treasury.png",
                "priority": 101,
                "is_positive_value_good": false,
                "description": "Hero action cost: -10%",
                "key": "wh_main_effect_agent_action_cost_mod",
                "value": -10
              },
              {
                "icon": "agent.png",
                "priority": 101,
                "is_positive_value_good": true,
                "description": "Hero action success chance: +1%",
                "key": "wh_main_effect_agent_action_success_chance",
                "value": 1
              }
            ]
          },
          {
            "effects": [
              {
                "icon": "treasury.png",
                "priority": 101,
                "is_positive_value_good": false,
                "description": "Hero action cost: -20%",
                "key": "wh_main_effect_agent_action_cost_mod",
                "value": -20
              },
              {
                "icon": "agent.png",
                "priority": 101,
                "is_positive_value_good": true,
                "description": "Hero action success chance: +3%",
                "key": "wh_main_effect_agent_action_success_chance",
                "value": 3
              }
            ]
          },
          {
            "effects": [
              {
                "icon": "treasury.png",
                "priority": 101,
                "is_positive_value_good": false,
                "description": "Hero action cost: -40%",
                "key": "wh_main_effect_agent_action_cost_mod",
                "value": -40
              },
              {
                "icon": "agent.png",
                "priority": 101,
                "is_positive_value_good": true,
                "description": "Hero action success chance: +6%",
                "key": "wh_main_effect_agent_action_success_chance",
                "value": 6
              }
            ]
          }
        ],
        "character_skill_key": "wh2_main_skill_all_hero_reduce_action_cost",
        "tier": 5,
        "indent": 5,
        "points_on_creation": 0,
        "required_num_parents": 0,
        "visible_in_ui": true
      },
      {
        "key": "mixu_skill_node_tmb_ramhotep_campaign_07",
        "image_path": "campaign_canopic_jars.png",
        "is_background_skill": false,
        "name": "Canopic Jar Hoarder",
        "description": "These jars contain the remains of many Liche Priests, which are useful for raising and binding a new force.",
        "levels": [
          {
            "effects": [
              {
                "icon": "canopic_jars.png",
                "priority": 3,
                "is_positive_value_good": true,
                "description": "Canopic Jars generated: 1 per turn",
                "key": "wh2_dlc09_pooled_resource_canopic_jars_characters",
                "value": 1
              }
            ]
          },
          {
            "effects": [
              {
                "icon": "canopic_jars.png",
                "priority": 3,
                "is_positive_value_good": true,
                "description": "Canopic Jars generated: 2 per turn",
                "key": "wh2_dlc09_pooled_resource_canopic_jars_characters",
                "value": 2
              }
            ]
          },
          {
            "effects": [
              {
                "icon": "canopic_jars.png",
                "priority": 3,
                "is_positive_value_good": true,
                "description": "Canopic Jars generated: 3 per turn",
                "key": "wh2_dlc09_pooled_resource_canopic_jars_characters",
                "value": 3
              }
            ]
          }
        ],
        "character_skill_key": "wh2_dlc09_skill_tmb_campaign_4",
        "tier": 6,
        "indent": 5,
        "points_on_creation": 0,
        "required_num_parents": 0,
        "visible_in_ui": true
      }
    ]
  ],
  "key": "tmb_ramhotep",
  "backgroundSkills": [
    {
      "key": "mixu_skill_node_tmb_ramhotep_innate",
      "image_path": "trait_tomb_kings.png",
      "is_background_skill": true,
      "name": "The Greatest Necrotect",
      "description": "Ramhotep the Visionary was perhaps the greatest Necrotect in history. His craftsmanship was second to none, and it is said that his statues in the Valley of Kings were so lifelike that it is said that the kings of Nehekhara believed the gods themselves had returned to the mortal world.",
      "levels": [
        {
          "effects": [
            {
              "icon": "",
              "priority": 0,
              "is_positive_value_good": true,
              "description": "Immortal",
              "key": "mixu_LL_enable_immortality",
              "value": 1
            },
            {
              "icon": "morale.png",
              "priority": 99,
              "is_positive_value_good": true,
              "description": "Leadership: +10 for all Construct units\n\t(Hero's army)",
              "key": "mixu_LL_leadership_tmb_constructs",
              "value": 10
            },
            {
              "icon": "armour.png",
              "priority": 100,
              "is_positive_value_good": true,
              "description": "Armour: +10 for all Construct units\n\t(Hero's army)",
              "key": "mixu_LL_armour_tmb_constructs",
              "value": 10
            }
          ]
        }
      ],
      "character_skill_node_set_key": "mixu_skill_node_set_tmb_ramhotep",
      "character_skill_key": "mixu_innate_tmb_ramhotep",
      "tier": 9,
      "indent": 6,
      "points_on_creation": 1,
      "required_num_parents": 0,
      "visible_in_ui": false
    },
    {
      "key": "mixu_skill_node_tmb_ramhotep_campaign_actions_dummy",
      "image_path": "battle_attack.png",
      "is_background_skill": false,
      "name": "Actions [HIDDEN]",
      "description": "",
      "levels": [
        {
          "effects": [
            {
              "icon": "",
              "priority": 0,
              "is_positive_value_good": true,
              "description": "",
              "key": "wh2_main_effect_agent_action_enable_engineer_assist_army_enhance_mobility",
              "value": 1
            },
            {
              "icon": "",
              "priority": 0,
              "is_positive_value_good": true,
              "description": "",
              "key": "wh2_main_effect_agent_action_enable_engineer_hinder_agent_wound",
              "value": 1
            },
            {
              "icon": "",
              "priority": 0,
              "is_positive_value_good": true,
              "description": "",
              "key": "wh2_main_effect_agent_action_enable_engineer_hinder_army_block_army",
              "value": 1
            },
            {
              "icon": "",
              "priority": 0,
              "is_positive_value_good": true,
              "description": "",
              "key": "wh2_main_effect_agent_action_enable_engineer_hinder_settlement_damage_walls",
              "value": 1
            },
            {
              "icon": "",
              "priority": 0,
              "is_positive_value_good": true,
              "description": "",
              "key": "wh2_main_effect_agent_action_enable_engineer_hinder_settlement_scout_settlement",
              "value": 1
            },
            {
              "icon": "",
              "priority": 0,
              "is_positive_value_good": true,
              "description": "",
              "key": "wh2_main_effect_agent_action_enable_engineer_passive_boost_income",
              "value": 1
            },
            {
              "icon": "income.png",
              "priority": 0,
              "is_positive_value_good": true,
              "description": "Income from all buildings: -5%\n\t(local province)",
              "key": "wh2_main_effect_agent_action_passive_boost_income_effect_negative",
              "value": -5
            },
            {
              "icon": "income.png",
              "priority": 0,
              "is_positive_value_good": true,
              "description": "Income from all buildings: +5%\n\t(local province)",
              "key": "wh2_main_effect_agent_action_passive_boost_income_effect_positive",
              "value": 5
            }
          ]
        }
      ],
      "character_skill_node_set_key": "mixu_skill_node_set_tmb_ramhotep",
      "character_skill_key": "wh2_dlc09_skill_all_dummy_agent_actions_tmb_necrotect",
      "tier": 0,
      "indent": 8,
      "points_on_creation": 1,
      "required_num_parents": 0,
      "visible_in_ui": false
    }
  ]
}
