{
  "skillTree": [
    [
      {
        "key": "wh_main_skill_node_chs_sigvald_unique_03",
        "image_path": "character_attack.png",
        "is_background_skill": false,
        "name": "Favoured Son",
        "description": "Slaanesh's favoured child has been granted the gift of preternatural swordsmanship.",
        "levels": [
          {
            "unlocked_at_rank": 8,
            "effects": [
              {
                "icon": "melee_character.png",
                "priority": 55,
                "is_positive_value_good": true,
                "description": "Melee attack: +12",
                "key": "wh_main_effect_character_stat_mod_melee_attack",
                "value": 12
              }
            ]
          }
        ],
        "character_skill_key": "wh_main_skill_chs_lord_unique_sigvald_favoured_son",
        "tier": 2,
        "indent": 0,
        "points_on_creation": 0,
        "required_num_parents": 0,
        "visible_in_ui": true
      },
      {
        "key": "wh_main_skill_node_chs_sigvald_unique_04",
        "image_path": "character_morale.png",
        "is_background_skill": false,
        "name": "Marked by Slaanesh",
        "description": "The beatific Mark of Slaanesh is branded into Sigvald's perfect body.",
        "levels": [
          {
            "unlocked_at_rank": 12,
            "effects": [
              {
                "icon": "morale_character.png",
                "priority": 6,
                "is_positive_value_good": true,
                "description": "Character's aura leadership effect: +5",
                "key": "wh_main_effect_character_stat_mod_personal_aura_morale_effect",
                "value": 5
              },
              {
                "icon": "dlc16_phase_charmed.png",
                "priority": 61,
                "is_positive_value_good": true,
                "description": "Enables charmed attacks",
                "key": "wh2_dlc16_enable_charmed_attacks",
                "value": 1
              }
            ]
          }
        ],
        "character_skill_key": "wh_main_skill_chs_lord_unique_sigvald_marked_by_slaanesh",
        "tier": 3,
        "indent": 0,
        "points_on_creation": 0,
        "required_num_parents": 0,
        "visible_in_ui": true
      },
      {
        "key": "wh_main_skill_node_chs_sigvald_unique_06",
        "image_path": "battle_speed.png",
        "is_background_skill": false,
        "name": "Hearts of Iron",
        "description": "The followers of Chaos need not to rest, they march on with iron hearts desperate to harvest souls.",
        "levels": [
          {
            "effects": [
              {
                "icon": "vigour.png",
                "priority": 101,
                "is_positive_value_good": false,
                "description": "Vigour loss reduction: -15%\n\t(Lord's army)",
                "key": "wh_main_effect_force_unit_stat_fatigue_resistance_large",
                "value": -15
              }
            ]
          }
        ],
        "character_skill_key": "wh_main_skill_chs_lord_battle_hearts_of_iron",
        "tier": 4,
        "indent": 0,
        "points_on_creation": 0,
        "required_num_parents": 0,
        "visible_in_ui": true
      },
      {
        "key": "wh_main_skill_node_chs_sigvald_unique_07",
        "image_path": "battle_general_ability.png",
        "is_background_skill": false,
        "name": "Voice of the Dark Gods",
        "description": "This Lord speaks with a dread booming voice - a gift from his Dark Masters to ensure obedience.",
        "levels": [
          {
            "effects": [
              {
                "icon": "general_ability.png",
                "priority": 5,
                "is_positive_value_good": true,
                "description": "Leadership aura size: +40%",
                "key": "wh_main_effect_character_stat_mod_personal_aura_size",
                "value": 40
              }
            ]
          }
        ],
        "character_skill_key": "wh_main_skill_chs_lord_battle_voice_of_the_dark_gods",
        "tier": 5,
        "indent": 0,
        "points_on_creation": 0,
        "required_num_parents": 0,
        "visible_in_ui": true
      },
      {
        "key": "wh_main_skill_node_chs_sigvald_unique_05",
        "image_path": "character_ward_save.png",
        "is_background_skill": false,
        "name": "Aura of Chaos",
        "description": "The shadow of the Ruinous Powers looms large, protecting those who bear their mark.",
        "levels": [
          {
            "unlocked_at_rank": 8,
            "effects": [
              {
                "icon": "resistance_missile.png",
                "priority": 55,
                "is_positive_value_good": true,
                "description": "Missile resistance: 10%",
                "key": "wh_main_effect_character_stat_mod_ward_save_missile",
                "value": 10
              }
            ]
          }
        ],
        "character_skill_key": "wh_main_skill_chs_all_unique_aura_of_chaos",
        "tier": 6,
        "indent": 0,
        "points_on_creation": 0,
        "required_num_parents": 0,
        "visible_in_ui": true
      }
    ],
    [
      {
        "key": "wh_dlc08_skill_chs_lord_unique_sigvald_0",
        "image_path": "character_morale.png",
        "is_background_skill": false,
        "name": "Egomaniacal",
        "description": "Being unable to contemplate anything other than their own perverse needs and desires would be a handicap for anyone else, but not so Sigvald the Magnificent.",
        "levels": [
          {
            "unlocked_at_rank": 12,
            "effects": [
              {
                "icon": "military_spending.png",
                "priority": 70,
                "is_positive_value_good": false,
                "description": "Upkeep: +25% for Chaos Lord and Chaos Sorcerer Lord\n\t(all armies factionwide)",
                "key": "wh_dlc08_effect_upkeep_chs_lord",
                "value": 25
              },
              {
                "icon": "morale.png",
                "priority": 102,
                "is_positive_value_good": true,
                "description": "Leadership: +5\n\t(Lord's army)",
                "key": "wh_main_effect_force_unit_stat_morale",
                "value": 5
              }
            ]
          }
        ],
        "character_skill_key": "wh_dlc08_skill_chs_lord_unique_sigvald_0",
        "tier": 0,
        "indent": 1,
        "points_on_creation": 0,
        "required_num_parents": 0,
        "visible_in_ui": true,
        "right_arrow": true
      },
      {
        "key": "wh_dlc08_skill_chs_lord_unique_sigvald_1",
        "image_path": "character_attack.png",
        "is_background_skill": false,
        "name": "Self-Obsessed",
        "description": "\"I know, I know - I truly am a perfect specimen. Hold the mirror a bit higher… higher! Yes that's right…\"",
        "levels": [
          {
            "effects": [
              {
                "icon": "melee_character.png",
                "priority": 55,
                "is_positive_value_good": true,
                "description": "Melee attack: +6",
                "key": "wh_main_effect_character_stat_mod_melee_attack",
                "value": 6
              },
              {
                "icon": "defence_character.png",
                "priority": 55,
                "is_positive_value_good": true,
                "description": "Melee defence: +6",
                "key": "wh_main_effect_character_stat_mod_melee_defence",
                "value": 6
              }
            ]
          }
        ],
        "character_skill_key": "wh_dlc08_skill_chs_lord_unique_sigvald_1",
        "tier": 1,
        "indent": 1,
        "points_on_creation": 0,
        "required_num_parents": 0,
        "visible_in_ui": true,
        "parent_required": [
          "wh_dlc08_skill_chs_lord_unique_sigvald_0"
        ],
        "boxed": true
      },
      {
        "key": "wh_dlc08_skill_chs_lord_unique_sigvald_2",
        "image_path": "character_armour.png",
        "is_background_skill": false,
        "name": "Stylish",
        "description": "\"What think you of this particular suit of armour? I think the gold really captures my best aspects - all of them hahahaha!\"",
        "levels": [
          {
            "effects": [
              {
                "icon": "armour.png",
                "priority": 101,
                "is_positive_value_good": true,
                "description": "Armour: +8\n\t(Lord's army)",
                "key": "wh_main_effect_force_unit_stat_armour",
                "value": 8
              },
              {
                "icon": "defence.png",
                "priority": 101,
                "is_positive_value_good": true,
                "description": "Melee defence: +6\n\t(Lord's army)",
                "key": "wh_main_effect_force_unit_stat_melee_defence",
                "value": 6
              }
            ]
          }
        ],
        "character_skill_key": "wh_dlc08_skill_chs_lord_unique_sigvald_2",
        "tier": 2,
        "indent": 1,
        "points_on_creation": 0,
        "required_num_parents": 0,
        "visible_in_ui": true,
        "parent_required": [
          "wh_dlc08_skill_chs_lord_unique_sigvald_0"
        ],
        "boxed": true
      },
      {
        "key": "wh_dlc08_skill_chs_lord_unique_sigvald_3",
        "image_path": "character_military_spending.png",
        "is_background_skill": false,
        "name": "Driven by Lust",
        "description": "Sigvald inspires fanatical devotion in his followers, for they know that in the aftermath of battle they may sate their most unholy lusts without restraint.",
        "levels": [
          {
            "effects": [
              {
                "icon": "military_spending.png",
                "priority": 70,
                "is_positive_value_good": false,
                "description": "Upkeep: -9% for all units\n\t(Lord's army)",
                "key": "wh_main_effect_force_all_campaign_upkeep",
                "value": -9
              },
              {
                "icon": "income.png",
                "priority": 101,
                "is_positive_value_good": true,
                "description": "Income from razing settlements: +15%",
                "key": "wh_main_effect_force_all_campaign_razing_income",
                "value": 15
              },
              {
                "icon": "income.png",
                "priority": 201,
                "is_positive_value_good": true,
                "description": "Income from post-battle loot: +15%",
                "key": "wh_main_effect_force_all_campaign_post_battle_loot_mod",
                "value": 15
              }
            ]
          }
        ],
        "character_skill_key": "wh_dlc08_skill_chs_lord_unique_sigvald_3",
        "tier": 3,
        "indent": 1,
        "points_on_creation": 0,
        "required_num_parents": 0,
        "visible_in_ui": true,
        "parent_required": [
          "wh_dlc08_skill_chs_lord_unique_sigvald_0"
        ],
        "boxed": true
      },
      {
        "key": "wh_dlc08_skill_chs_lord_unique_sigvald_4",
        "image_path": "character_subterfuge.png",
        "is_background_skill": false,
        "name": "Born to Serve",
        "description": "Sigvald's sycophantic minions will do anything to stay in his favour, not realising that he cares for none but himself and the attention of the Dark Prince, Slaanesh.",
        "levels": [
          {
            "effects": [
              {
                "icon": "treasury.png",
                "priority": 101,
                "is_positive_value_good": false,
                "description": "Hero action cost: -9%\n\t(all Heroes)",
                "key": "wh_main_effect_agent_action_cost_mod",
                "value": -9
              },
              {
                "icon": "agent.png",
                "priority": 101,
                "is_positive_value_good": true,
                "description": "Hero action success chance: +9%\n\t(all Heroes)",
                "key": "wh_main_effect_agent_action_success_chance",
                "value": 9
              }
            ]
          }
        ],
        "character_skill_key": "wh_dlc08_skill_chs_lord_unique_sigvald_4",
        "tier": 4,
        "indent": 1,
        "points_on_creation": 0,
        "required_num_parents": 0,
        "visible_in_ui": true,
        "parent_required": [
          "wh_dlc08_skill_chs_lord_unique_sigvald_0"
        ],
        "right_arrow": true,
        "boxed": true
      },
      {
        "key": "wh_dlc08_skill_chs_lord_unique_sigvald_5",
        "image_path": "causes_terror.png",
        "is_background_skill": false,
        "name": "Unworthy",
        "description": "On sight of Sigvald's undeniable magnificence the enemy must confront their own obvious inadequacies, and despair.",
        "levels": [
          {
            "effects": [
              {
                "icon": "attribute_causes_fear.png",
                "priority": 620,
                "is_positive_value_good": true,
                "description": "Attribute: Causes Fear",
                "key": "wh_main_effect_unit_enable_attribute_fear",
                "value": 1
              },
              {
                "icon": "attribute_causes_terror.png",
                "priority": 620,
                "is_positive_value_good": true,
                "description": "Attribute: Causes Terror",
                "key": "wh_main_effect_unit_enable_attribute_terror",
                "value": 1
              }
            ]
          }
        ],
        "character_skill_key": "wh_dlc08_skill_chs_lord_unique_sigvald_5",
        "tier": 5,
        "indent": 1,
        "points_on_creation": 0,
        "required_num_parents": 4,
        "visible_in_ui": true,
        "parent_subset_required": [
          "wh_dlc08_skill_chs_lord_unique_sigvald_1",
          "wh_dlc08_skill_chs_lord_unique_sigvald_2",
          "wh_dlc08_skill_chs_lord_unique_sigvald_3",
          "wh_dlc08_skill_chs_lord_unique_sigvald_4"
        ]
      }
    ],
    [
      {
        "key": "wh_main_skill_node_chs_sigvald_self_01",
        "image_path": "character_damage.png",
        "is_background_skill": false,
        "name": "Eye of the Gods",
        "description": "The Warriors of Chaos are the playthings of Gods and given many gifts, including formidable fighting skills.",
        "levels": [
          {
            "effects": [
              {
                "icon": "weapon_damage_character.png",
                "priority": 101,
                "is_positive_value_good": true,
                "description": "Weapon strength: +7% (when attacking)",
                "key": "wh_main_effect_force_unit_stat_melee_damage_attacking",
                "value": 7
              }
            ]
          }
        ],
        "character_skill_key": "wh_main_skill_chs_lord_self_eye_of_the_gods",
        "tier": 0,
        "indent": 2,
        "points_on_creation": 0,
        "required_num_parents": 0,
        "visible_in_ui": true,
        "right_arrow": true
      },
      {
        "key": "wh_main_skill_node_chs_sigvald_self_02",
        "image_path": "character_charge.png",
        "is_background_skill": false,
        "name": "Devastating Charge",
        "description": "Some creatures charge home with such fury that the very ground shakes beneath their feet.",
        "levels": [
          {
            "effects": [
              {
                "icon": "charge_character.png",
                "priority": 55,
                "is_positive_value_good": true,
                "description": "Charge bonus: +15",
                "key": "wh_main_effect_character_stat_mod_charge_add",
                "value": 15
              }
            ]
          },
          {
            "effects": [
              {
                "icon": "charge_character.png",
                "priority": 55,
                "is_positive_value_good": true,
                "description": "Charge bonus: +30",
                "key": "wh_main_effect_character_stat_mod_charge_add",
                "value": 30
              }
            ]
          }
        ],
        "character_skill_key": "wh2_dlc11_skill_all_lord_self_devastating_charge",
        "tier": 1,
        "indent": 2,
        "points_on_creation": 0,
        "required_num_parents": 0,
        "visible_in_ui": true,
        "parent_required": [
          "wh_main_skill_node_chs_sigvald_self_01"
        ],
        "boxed": true
      },
      {
        "key": "wh_main_skill_node_chs_sigvald_self_03",
        "image_path": "character_armour.png",
        "is_background_skill": false,
        "name": "Thick-Skinned",
        "description": "Creatures with tough hides or some kind of natural armour are tough nuts to crack - even a powerful attack may fall foul of their thick-skin.",
        "levels": [
          {
            "effects": [
              {
                "icon": "armour_character.png",
                "priority": 55,
                "is_positive_value_good": true,
                "description": "Armour: +7",
                "key": "wh_main_effect_character_stat_mod_armour",
                "value": 7
              }
            ]
          },
          {
            "effects": [
              {
                "icon": "armour_character.png",
                "priority": 55,
                "is_positive_value_good": true,
                "description": "Armour: +15",
                "key": "wh_main_effect_character_stat_mod_armour",
                "value": 15
              }
            ]
          }
        ],
        "character_skill_key": "wh2_dlc11_skill_all_lord_self_thick-skinned",
        "tier": 2,
        "indent": 2,
        "points_on_creation": 0,
        "required_num_parents": 0,
        "visible_in_ui": true,
        "parent_required": [
          "wh_main_skill_node_chs_sigvald_self_01"
        ],
        "boxed": true
      },
      {
        "key": "wh_main_skill_node_chs_sigvald_self_04",
        "image_path": "character_defence.png",
        "is_background_skill": false,
        "name": "Hard to Hit",
        "description": "Hand-to-hand combat is a lethal match of cut and thrust. However, it’s not all about offensive strikes; parries and other defensive moves can also win the day.",
        "levels": [
          {
            "effects": [
              {
                "icon": "defence_character.png",
                "priority": 55,
                "is_positive_value_good": true,
                "description": "Melee defence: +6",
                "key": "wh_main_effect_character_stat_mod_melee_defence",
                "value": 6
              }
            ]
          },
          {
            "effects": [
              {
                "icon": "defence_character.png",
                "priority": 55,
                "is_positive_value_good": true,
                "description": "Melee defence: +12",
                "key": "wh_main_effect_character_stat_mod_melee_defence",
                "value": 12
              }
            ]
          }
        ],
        "character_skill_key": "wh2_dlc11_skill_all_lord_self_hard_to_hit",
        "tier": 3,
        "indent": 2,
        "points_on_creation": 0,
        "required_num_parents": 0,
        "visible_in_ui": true,
        "parent_required": [
          "wh_main_skill_node_chs_sigvald_self_01"
        ],
        "boxed": true
      },
      {
        "key": "wh_main_skill_node_chs_sigvald_self_05",
        "image_path": "character_attack.png",
        "is_background_skill": false,
        "name": "Deadly Blade",
        "description": "A deadly blade is especially lethal when in the hands of this master death-maker, killer and slaughterer!",
        "levels": [
          {
            "effects": [
              {
                "icon": "melee_character.png",
                "priority": 55,
                "is_positive_value_good": true,
                "description": "Melee attack: +6",
                "key": "wh_main_effect_character_stat_mod_melee_attack",
                "value": 6
              }
            ]
          },
          {
            "effects": [
              {
                "icon": "melee_character.png",
                "priority": 55,
                "is_positive_value_good": true,
                "description": "Melee attack: +12",
                "key": "wh_main_effect_character_stat_mod_melee_attack",
                "value": 12
              }
            ]
          }
        ],
        "character_skill_key": "wh2_dlc11_skill_all_lord_self_deadly_blade",
        "tier": 4,
        "indent": 2,
        "points_on_creation": 0,
        "required_num_parents": 0,
        "visible_in_ui": true,
        "parent_required": [
          "wh_main_skill_node_chs_sigvald_self_01"
        ],
        "right_arrow": true,
        "boxed": true
      },
      {
        "key": "wh_main_skill_node_chs_sigvald_self_06",
        "image_path": "wh_main_character_abilities_foe_seeker.png",
        "is_background_skill": false,
        "name": "Foe-Seeker",
        "description": " From one bloodied, lifeless corpse to the next, this one is always looking for the next adversary to best.",
        "levels": [
          {
            "effects": [
              {
                "icon": "general_ability.png",
                "priority": 600,
                "is_positive_value_good": true,
                "description": "Ability: \"Foe-Seeker\"",
                "related_abilities": [
                  {
                    "effect": "wh_main_effect_ability_enable_foe-seeker",
                    "bonus_value_id": "enable",
                    "unit_ability": {
                      "key": "wh_main_character_abilities_foe_seeker",
                      "icon_name": "wh_main_character_abilities_foe_seeker",
                      "overpower_option": "",
                      "type": {
                        "key": "wh_type_augment",
                        "icon_path": "icon_spell_augment.png",
                        "description": "Augment"
                      },
                      "is_hidden_in_ui": false,
                      "description": "Foe-Seeker",
                      "active_time": 25,
                      "recharge_time": 60,
                      "effect_range": 0,
                      "target_friends": false,
                      "target_enemies": false,
                      "target_ground": false,
                      "target_intercept_range": 0,
                      "target_self": false,
                      "phases": [
                        {
                          "duration": 25,
                          "effect_type": "positive",
                          "fatigue_change_ratio": -0.18,
                          "max_damaged_entities": -1,
                          "is_hidden_in_ui": false,
                          "stat_effects": [
                            {
                              "value": 1.3,
                              "stat": "scalar_speed",
                              "how": "mult",
                              "description": "x1.3 Speed",
                              "sort_order": 10,
                              "icon": "icon_stat_speed.png"
                            }
                          ]
                        }
                      ]
                    }
                  }
                ],
                "key": "wh_main_effect_ability_enable_foe-seeker",
                "value": 1
              }
            ]
          }
        ],
        "character_skill_key": "wh_main_skill_all_all_self_foe-seeker",
        "tier": 5,
        "indent": 2,
        "points_on_creation": 0,
        "required_num_parents": 4,
        "visible_in_ui": true,
        "parent_subset_required": [
          "wh_main_skill_node_chs_sigvald_self_02",
          "wh_main_skill_node_chs_sigvald_self_03",
          "wh_main_skill_node_chs_sigvald_self_04",
          "wh_main_skill_node_chs_sigvald_self_05"
        ],
        "right_arrow": true
      },
      {
        "key": "wh_main_skill_node_chs_sigvald_self_07",
        "image_path": "character_damage.png",
        "is_background_skill": false,
        "name": "Wound-Maker",
        "description": "Such is their power and ferocity, a wound-maker will ravage the foe, cutting and pulverising until there is only one exit - death.",
        "levels": [
          {
            "effects": [
              {
                "icon": "weapon_damage_character.png",
                "priority": 55,
                "is_positive_value_good": true,
                "description": "Weapon strength: +10%",
                "key": "wh_main_effect_character_stat_mod_melee_damage",
                "value": 10
              }
            ]
          },
          {
            "effects": [
              {
                "icon": "weapon_damage_character.png",
                "priority": 55,
                "is_positive_value_good": true,
                "description": "Weapon strength: +20%",
                "key": "wh_main_effect_character_stat_mod_melee_damage",
                "value": 20
              }
            ]
          }
        ],
        "character_skill_key": "wh2_dlc11_skill_all_lord_self_wound-maker",
        "tier": 6,
        "indent": 2,
        "points_on_creation": 0,
        "required_num_parents": 0,
        "visible_in_ui": true,
        "parent_required": [
          "wh_main_skill_node_chs_sigvald_self_06"
        ],
        "boxed": true
      },
      {
        "key": "wh_main_skill_node_chs_sigvald_self_08",
        "image_path": "character_health.png",
        "is_background_skill": false,
        "name": "Scarred Veteran",
        "description": "The scars on this storied warrior reveal a veteran of many battles, a being not easy to kill and one worthy of respect and fear.",
        "levels": [
          {
            "effects": [
              {
                "icon": "health_character.png",
                "priority": 55,
                "is_positive_value_good": true,
                "description": "Hit points: +7%",
                "key": "wh_main_effect_character_stat_mod_unit_health",
                "value": 7
              }
            ]
          },
          {
            "effects": [
              {
                "icon": "health_character.png",
                "priority": 55,
                "is_positive_value_good": true,
                "description": "Hit points: +15%",
                "key": "wh_main_effect_character_stat_mod_unit_health",
                "value": 15
              }
            ]
          }
        ],
        "character_skill_key": "wh2_dlc11_skill_all_lord_self_scarred_veteran",
        "tier": 7,
        "indent": 2,
        "points_on_creation": 0,
        "required_num_parents": 0,
        "visible_in_ui": true,
        "parent_required": [
          "wh_main_skill_node_chs_sigvald_self_06"
        ],
        "boxed": true
      },
      {
        "key": "wh_main_skill_node_chs_sigvald_self_09",
        "image_path": "character_morale.png",
        "is_background_skill": false,
        "name": "Indomitable",
        "description": "The iron will and indomitable presence of this leader ensures their followers remain steadfast when facing peril.",
        "levels": [
          {
            "effects": [
              {
                "icon": "morale_character.png",
                "priority": 55,
                "is_positive_value_good": true,
                "description": "Leadership: +6",
                "key": "wh_main_effect_character_stat_mod_morale",
                "value": 6
              }
            ]
          },
          {
            "effects": [
              {
                "icon": "morale_character.png",
                "priority": 55,
                "is_positive_value_good": true,
                "description": "Leadership: +12",
                "key": "wh_main_effect_character_stat_mod_morale",
                "value": 12
              }
            ]
          }
        ],
        "character_skill_key": "wh2_dlc11_skill_all_lord_self_self_indomitable",
        "tier": 8,
        "indent": 2,
        "points_on_creation": 0,
        "required_num_parents": 0,
        "visible_in_ui": true,
        "parent_required": [
          "wh_main_skill_node_chs_sigvald_self_06"
        ],
        "boxed": true
      },
      {
        "key": "wh_main_skill_node_chs_sigvald_self_10",
        "image_path": "character_defence.png",
        "is_background_skill": false,
        "name": "Blade Shield",
        "description": "A blade that sings in defence will not let its wielder be penetrated.",
        "levels": [
          {
            "effects": [
              {
                "icon": "defence_character.png",
                "priority": 55,
                "is_positive_value_good": true,
                "description": "Melee defence: +6",
                "key": "wh_main_effect_character_stat_mod_melee_defence",
                "value": 6
              }
            ]
          },
          {
            "effects": [
              {
                "icon": "defence_character.png",
                "priority": 55,
                "is_positive_value_good": true,
                "description": "Melee defence: +12",
                "key": "wh_main_effect_character_stat_mod_melee_defence",
                "value": 12
              }
            ]
          }
        ],
        "character_skill_key": "wh2_dlc11_skill_all_lord_self_blade_shield",
        "tier": 9,
        "indent": 2,
        "points_on_creation": 0,
        "required_num_parents": 0,
        "visible_in_ui": true,
        "parent_required": [
          "wh_main_skill_node_chs_sigvald_self_06"
        ],
        "right_arrow": true,
        "boxed": true
      },
      {
        "key": "wh_main_skill_node_chs_sigvald_self_11",
        "image_path": "wh_main_character_abilities_deadly_onslaught.png",
        "is_background_skill": false,
        "name": "Deadly Onslaught",
        "description": "The war is endless. The cycle of charging, clashing, and bloody hand-to-hand fighting is without end. It will never stop.",
        "levels": [
          {
            "effects": [
              {
                "icon": "general_ability.png",
                "priority": 600,
                "is_positive_value_good": true,
                "description": "Ability: \"Deadly Onslaught\"",
                "related_abilities": [
                  {
                    "effect": "wh_main_effect_ability_enable_deadly_onslaught",
                    "bonus_value_id": "enable",
                    "unit_ability": {
                      "key": "wh_main_character_abilities_deadly_onslaught",
                      "icon_name": "wh_main_character_abilities_deadly_onslaught",
                      "overpower_option": "",
                      "type": {
                        "key": "wh_type_augment",
                        "icon_path": "icon_spell_augment.png",
                        "description": "Augment"
                      },
                      "is_hidden_in_ui": false,
                      "description": "Deadly Onslaught",
                      "active_time": 31,
                      "recharge_time": 90,
                      "effect_range": 0,
                      "target_friends": false,
                      "target_enemies": false,
                      "target_ground": false,
                      "target_intercept_range": 0,
                      "target_self": false,
                      "phases": [
                        {
                          "duration": 31,
                          "effect_type": "positive",
                          "is_hidden_in_ui": false,
                          "stat_effects": [
                            {
                              "value": 1.4,
                              "stat": "stat_charge_bonus",
                              "how": "mult",
                              "description": "x1.4 Charge Bonus",
                              "sort_order": 4,
                              "icon": "icon_stat_charge_bonus.png"
                            },
                            {
                              "value": 1.3,
                              "stat": "stat_melee_damage_ap",
                              "how": "mult",
                              "description": "x1.3 Armour-Piercing Weapon Damage",
                              "sort_order": 0,
                              "icon": "modifier_icon_armour_piercing.png"
                            },
                            {
                              "value": 1.3,
                              "stat": "stat_melee_damage_base",
                              "how": "mult",
                              "description": "x1.3 Base Weapon Damage",
                              "sort_order": 0,
                              "icon": "icon_stat_damage_base.png"
                            }
                          ]
                        }
                      ]
                    }
                  }
                ],
                "key": "wh_main_effect_ability_enable_deadly_onslaught",
                "value": 1
              }
            ],
            "blocks_character_skill_key": [
              "wh_dlc05_skill_wef_general_personal_buff_ranged_ability_high_tier_killer_2"
            ]
          }
        ],
        "character_skill_key": "wh_main_skill_all_all_self_deadly_onslaught",
        "tier": 10,
        "indent": 2,
        "points_on_creation": 0,
        "required_num_parents": 4,
        "visible_in_ui": true,
        "parent_subset_required": [
          "wh_main_skill_node_chs_sigvald_self_07",
          "wh_main_skill_node_chs_sigvald_self_08",
          "wh_main_skill_node_chs_sigvald_self_09",
          "wh_main_skill_node_chs_sigvald_self_10"
        ]
      }
    ],
    [],
    [
      {
        "key": "wh_main_skill_node_chs_sigvald_battle_01",
        "image_path": "battle_morale.png",
        "is_background_skill": false,
        "name": "Dominating Presence",
        "description": "A Chaos Lord dominates – lesser beings cringe from a being that is so intently under scrutiny from the Dark Gods.",
        "levels": [
          {
            "effects": [
              {
                "icon": "morale_character.png",
                "priority": 6,
                "is_positive_value_good": true,
                "description": "Character's aura leadership effect: +5",
                "key": "wh_main_effect_character_stat_mod_personal_aura_morale_effect",
                "value": 5
              }
            ]
          }
        ],
        "character_skill_key": "wh_main_skill_chs_lord_battle_dominating_presence",
        "tier": 0,
        "indent": 4,
        "points_on_creation": 0,
        "required_num_parents": 0,
        "visible_in_ui": true,
        "right_arrow": true
      },
      {
        "key": "wh_main_skill_node_chs_sigvald_battle_02",
        "image_path": "battle_defence.png",
        "is_background_skill": false,
        "name": "Chaos Vanguard",
        "description": "To the Northmen, there is no greater honour than to fight and perish under the gaze of the Gods.",
        "levels": [
          {
            "effects": [
              {
                "icon": "defence.png",
                "priority": 111,
                "is_positive_value_good": true,
                "description": "Melee defence: +4 for Chaos Marauders, Aspiring Champions, and Forsaken units\n\t(Lord's army)",
                "key": "wh2_dlc11_effect_skill_melee_defence_increase_chs_marauder_aspiring_champions_forsaken",
                "value": 4
              }
            ]
          },
          {
            "effects": [
              {
                "icon": "armour.png",
                "priority": 110,
                "is_positive_value_good": true,
                "description": "Armour: +6 for Chaos Marauders, Aspiring Champions, and Forsaken units\n\t(Lord's army)",
                "key": "wh2_dlc11_effect_skill_armour_increase_chs_marauder_aspiring_champions_forsaken",
                "value": 6
              },
              {
                "icon": "defence.png",
                "priority": 111,
                "is_positive_value_good": true,
                "description": "Melee defence: +6 for Chaos Marauders, Aspiring Champions, and Forsaken units\n\t(Lord's army)",
                "key": "wh2_dlc11_effect_skill_melee_defence_increase_chs_marauder_aspiring_champions_forsaken",
                "value": 6
              }
            ]
          },
          {
            "effects": [
              {
                "icon": "armour.png",
                "priority": 110,
                "is_positive_value_good": true,
                "description": "Armour: +12 for Chaos Marauders, Aspiring Champions, and Forsaken units\n\t(Lord's army)",
                "key": "wh2_dlc11_effect_skill_armour_increase_chs_marauder_aspiring_champions_forsaken",
                "value": 12
              },
              {
                "icon": "defence.png",
                "priority": 111,
                "is_positive_value_good": true,
                "description": "Melee defence: +8 for Chaos Marauders, Aspiring Champions, and Forsaken units\n\t(Lord's army)",
                "key": "wh2_dlc11_effect_skill_melee_defence_increase_chs_marauder_aspiring_champions_forsaken",
                "value": 8
              }
            ]
          }
        ],
        "character_skill_key": "wh2_dlc11_skill_chs_army_buff_chaos_vanguard",
        "tier": 1,
        "indent": 4,
        "points_on_creation": 0,
        "required_num_parents": 0,
        "visible_in_ui": true,
        "parent_required": [
          "wh_main_skill_node_chs_sigvald_battle_01"
        ],
        "boxed": true
      },
      {
        "key": "wh_main_skill_node_chs_sigvald_battle_03",
        "image_path": "battle_charge.png",
        "is_background_skill": false,
        "name": "Savage Bloodlust",
        "description": "Khorne’s will imbues his creatures with a vicious, unslakeable hunger for battle.",
        "levels": [
          {
            "effects": [
              {
                "icon": "charge.png",
                "priority": 121,
                "is_positive_value_good": true,
                "description": "Charge bonus: +6 for Marauder Horsemen, Marauder Horsemaster, Chaos Warhounds, and Chaos Feral Manticore units\n\t(Lord's army)",
                "key": "wh2_dlc11_effect_skill_charge_increase_chs_marauder_horsemen_warhounds_manticore",
                "value": 6
              }
            ]
          },
          {
            "effects": [
              {
                "icon": "melee.png",
                "priority": 109,
                "is_positive_value_good": true,
                "description": "Melee attack: +4 for Marauder Horsemen, Marauder Horsemaster, Chaos Warhounds, and Chaos Feral Manticore units\n\t(Lord's army)",
                "key": "wh2_dlc11_effect_skill_melee_attack_increase_chs_marauder_horsemen_warhounds_manticore",
                "value": 4
              },
              {
                "icon": "charge.png",
                "priority": 121,
                "is_positive_value_good": true,
                "description": "Charge bonus: +9 for Marauder Horsemen, Marauder Horsemaster, Chaos Warhounds, and Chaos Feral Manticore units\n\t(Lord's army)",
                "key": "wh2_dlc11_effect_skill_charge_increase_chs_marauder_horsemen_warhounds_manticore",
                "value": 9
              }
            ]
          },
          {
            "effects": [
              {
                "icon": "melee.png",
                "priority": 109,
                "is_positive_value_good": true,
                "description": "Melee attack: +8 for Marauder Horsemen, Marauder Horsemaster, Chaos Warhounds, and Chaos Feral Manticore units\n\t(Lord's army)",
                "key": "wh2_dlc11_effect_skill_melee_attack_increase_chs_marauder_horsemen_warhounds_manticore",
                "value": 8
              },
              {
                "icon": "charge.png",
                "priority": 121,
                "is_positive_value_good": true,
                "description": "Charge bonus: +12 for Marauder Horsemen, Marauder Horsemaster, Chaos Warhounds, and Chaos Feral Manticore units\n\t(Lord's army)",
                "key": "wh2_dlc11_effect_skill_charge_increase_chs_marauder_horsemen_warhounds_manticore",
                "value": 12
              }
            ]
          }
        ],
        "character_skill_key": "wh2_dlc11_skill_chs_army_buff_savage_bloodlust",
        "tier": 2,
        "indent": 4,
        "points_on_creation": 0,
        "required_num_parents": 0,
        "visible_in_ui": true,
        "parent_required": [
          "wh_main_skill_node_chs_sigvald_battle_01"
        ],
        "boxed": true
      },
      {
        "key": "wh_main_skill_node_chs_sigvald_battle_04",
        "image_path": "battle_defence.png",
        "is_background_skill": false,
        "name": "Blessed by Chaos",
        "description": "Unnatural strength, an aura of dark menace, an unwavering devotion to the Chaos Gods – some warriors have undoubtedly been touched by the Ruinous Ones.",
        "levels": [
          {
            "effects": [
              {
                "icon": "defence.png",
                "priority": 111,
                "is_positive_value_good": true,
                "description": "Melee defence: +4 for Chaos Warriors, Chaos Spawn, and Chosen units\n\t(Lord's army)",
                "key": "wh2_dlc11_effect_skill_melee_defence_increase_chs_chosen_spawn_chaos_warriors",
                "value": 4
              }
            ]
          },
          {
            "effects": [
              {
                "icon": "weapon_damage.png",
                "priority": 108,
                "is_positive_value_good": true,
                "description": "Weapon strength: +6% for Chaos Warriors, Chaos Spawn, and Chosen units\n\t(Lord's army)",
                "key": "wh2_dlc11_effect_skill_weapon_damage_increase_chs_chosen_spawn_chaos_warriors",
                "value": 6
              },
              {
                "icon": "defence.png",
                "priority": 111,
                "is_positive_value_good": true,
                "description": "Melee defence: +6 for Chaos Warriors, Chaos Spawn, and Chosen units\n\t(Lord's army)",
                "key": "wh2_dlc11_effect_skill_melee_defence_increase_chs_chosen_spawn_chaos_warriors",
                "value": 6
              }
            ]
          },
          {
            "effects": [
              {
                "icon": "weapon_damage.png",
                "priority": 108,
                "is_positive_value_good": true,
                "description": "Weapon strength: +12% for Chaos Warriors, Chaos Spawn, and Chosen units\n\t(Lord's army)",
                "key": "wh2_dlc11_effect_skill_weapon_damage_increase_chs_chosen_spawn_chaos_warriors",
                "value": 12
              },
              {
                "icon": "defence.png",
                "priority": 111,
                "is_positive_value_good": true,
                "description": "Melee defence: +8 for Chaos Warriors, Chaos Spawn, and Chosen units\n\t(Lord's army)",
                "key": "wh2_dlc11_effect_skill_melee_defence_increase_chs_chosen_spawn_chaos_warriors",
                "value": 8
              }
            ]
          }
        ],
        "character_skill_key": "wh2_dlc11_skill_chs_army_buff_blessed_by_chaos",
        "tier": 3,
        "indent": 4,
        "points_on_creation": 0,
        "required_num_parents": 0,
        "visible_in_ui": true,
        "parent_required": [
          "wh_main_skill_node_chs_sigvald_battle_01"
        ],
        "boxed": true
      },
      {
        "key": "wh_main_skill_node_chs_sigvald_battle_05",
        "image_path": "battle_charge.png",
        "is_background_skill": false,
        "name": "Hammer into Anvil",
        "description": "Breaking bones and ending lives, the armies of Chaos strike like an unholy hammer crashing through their enemies' ranks.",
        "levels": [
          {
            "effects": [
              {
                "icon": "charge.png",
                "priority": 121,
                "is_positive_value_good": true,
                "description": "Charge bonus: +6 for Dragon Ogres, Chaos Knights, Gorebeast Chariot, and Chaos Chariot units\n\t(Lord's army)",
                "key": "wh2_dlc11_effect_skill_charge_increase_chs_dragon_ogres_chaos_knights_chariots",
                "value": 6
              }
            ]
          },
          {
            "effects": [
              {
                "icon": "melee.png",
                "priority": 109,
                "is_positive_value_good": true,
                "description": "Melee attack: +4 for Dragon Ogres, Chaos Knights, Gorebeast Chariot, and Chaos Chariot units\n\t(Lord's army)",
                "key": "wh2_dlc11_effect_skill_melee_attack_increase_chs_dragon_ogres_chaos_knights_chariots",
                "value": 4
              },
              {
                "icon": "charge.png",
                "priority": 121,
                "is_positive_value_good": true,
                "description": "Charge bonus: +9 for Dragon Ogres, Chaos Knights, Gorebeast Chariot, and Chaos Chariot units\n\t(Lord's army)",
                "key": "wh2_dlc11_effect_skill_charge_increase_chs_dragon_ogres_chaos_knights_chariots",
                "value": 9
              }
            ]
          },
          {
            "effects": [
              {
                "icon": "melee.png",
                "priority": 109,
                "is_positive_value_good": true,
                "description": "Melee attack: +8 for Dragon Ogres, Chaos Knights, Gorebeast Chariot, and Chaos Chariot units\n\t(Lord's army)",
                "key": "wh2_dlc11_effect_skill_melee_attack_increase_chs_dragon_ogres_chaos_knights_chariots",
                "value": 8
              },
              {
                "icon": "charge.png",
                "priority": 121,
                "is_positive_value_good": true,
                "description": "Charge bonus: +12 for Dragon Ogres, Chaos Knights, Gorebeast Chariot, and Chaos Chariot units\n\t(Lord's army)",
                "key": "wh2_dlc11_effect_skill_charge_increase_chs_dragon_ogres_chaos_knights_chariots",
                "value": 12
              }
            ]
          }
        ],
        "character_skill_key": "wh2_dlc11_skill_chs_army_buff_hammer_to_the_anvil",
        "tier": 4,
        "indent": 4,
        "points_on_creation": 0,
        "required_num_parents": 0,
        "visible_in_ui": true,
        "parent_required": [
          "wh_main_skill_node_chs_sigvald_battle_01"
        ],
        "boxed": true
      },
      {
        "key": "wh_main_skill_node_chs_sigvald_battle_06",
        "image_path": "battle_attack.png",
        "is_background_skill": false,
        "name": "Monstrous Strength",
        "description": "Hulks of pure muscle, held upright by unsullied hatred, can crush a man with a frightening lack of effort.",
        "levels": [
          {
            "effects": [
              {
                "icon": "melee.png",
                "priority": 109,
                "is_positive_value_good": true,
                "description": "Melee attack: +4 for Dragon Ogre Shaggoth, Chaos Trolls, and Chaos Giant units\n\t(Lord's army)",
                "key": "wh2_dlc11_effect_skill_melee_attack_increase_chs_dragon_ogre_shaggoth_trolls_giant",
                "value": 4
              }
            ]
          },
          {
            "effects": [
              {
                "icon": "weapon_damage.png",
                "priority": 108,
                "is_positive_value_good": true,
                "description": "Weapon strength: +6% for Dragon Ogre Shaggoth, Chaos Trolls, and Chaos Giant units\n\t(Lord's army)",
                "key": "wh2_dlc11_effect_skill_weapon_damage_increase_chs_dragon_ogre_shaggoth_trolls_giant",
                "value": 6
              },
              {
                "icon": "melee.png",
                "priority": 109,
                "is_positive_value_good": true,
                "description": "Melee attack: +6 for Dragon Ogre Shaggoth, Chaos Trolls, and Chaos Giant units\n\t(Lord's army)",
                "key": "wh2_dlc11_effect_skill_melee_attack_increase_chs_dragon_ogre_shaggoth_trolls_giant",
                "value": 6
              }
            ]
          },
          {
            "effects": [
              {
                "icon": "weapon_damage.png",
                "priority": 108,
                "is_positive_value_good": true,
                "description": "Weapon strength: +12% for Dragon Ogre Shaggoth, Chaos Trolls, and Chaos Giant units\n\t(Lord's army)",
                "key": "wh2_dlc11_effect_skill_weapon_damage_increase_chs_dragon_ogre_shaggoth_trolls_giant",
                "value": 12
              },
              {
                "icon": "melee.png",
                "priority": 109,
                "is_positive_value_good": true,
                "description": "Melee attack: +8 for Dragon Ogre Shaggoth, Chaos Trolls, and Chaos Giant units\n\t(Lord's army)",
                "key": "wh2_dlc11_effect_skill_melee_attack_increase_chs_dragon_ogre_shaggoth_trolls_giant",
                "value": 8
              }
            ]
          }
        ],
        "character_skill_key": "wh2_dlc11_skill_chs_army_buff_monstrous_strength",
        "tier": 5,
        "indent": 4,
        "points_on_creation": 0,
        "required_num_parents": 0,
        "visible_in_ui": true,
        "parent_required": [
          "wh_main_skill_node_chs_sigvald_battle_01"
        ],
        "boxed": true
      },
      {
        "key": "wh_main_skill_node_chs_sigvald_battle_07",
        "image_path": "battle_ammo.png",
        "is_background_skill": false,
        "name": "Doomfire",
        "description": "Doomfire is a gift from Khorne, to ensure the Hellcannons speak with extra fury.",
        "levels": [
          {
            "effects": [
              {
                "icon": "ammo.png",
                "priority": 201,
                "is_positive_value_good": true,
                "description": "Ammunition: +10% for Hellcannon units\n\t(Lord's army)",
                "key": "wh2_dlc11_effect_skill_ammo_increase_chs_hellcannon",
                "value": 10
              }
            ]
          },
          {
            "effects": [
              {
                "icon": "ammo.png",
                "priority": 201,
                "is_positive_value_good": true,
                "description": "Ammunition: +15% for Hellcannon units\n\t(Lord's army)",
                "key": "wh2_dlc11_effect_skill_ammo_increase_chs_hellcannon",
                "value": 15
              },
              {
                "icon": "ranged_damage.png",
                "priority": 203,
                "is_positive_value_good": true,
                "description": "Missile strength: +6% for Hellcannon units\n\t(Lord's army)",
                "key": "wh2_dlc11_effect_skill_missile_damage_increase_chs_hellcannon",
                "value": 6
              }
            ]
          },
          {
            "effects": [
              {
                "icon": "ammo.png",
                "priority": 201,
                "is_positive_value_good": true,
                "description": "Ammunition: +20% for Hellcannon units\n\t(Lord's army)",
                "key": "wh2_dlc11_effect_skill_ammo_increase_chs_hellcannon",
                "value": 20
              },
              {
                "icon": "ranged_damage.png",
                "priority": 203,
                "is_positive_value_good": true,
                "description": "Missile strength: +12% for Hellcannon units\n\t(Lord's army)",
                "key": "wh2_dlc11_effect_skill_missile_damage_increase_chs_hellcannon",
                "value": 12
              }
            ]
          }
        ],
        "character_skill_key": "wh2_dlc11_skill_chs_army_buff_doomfire",
        "tier": 6,
        "indent": 4,
        "points_on_creation": 0,
        "required_num_parents": 0,
        "visible_in_ui": true,
        "parent_required": [
          "wh_main_skill_node_chs_sigvald_battle_01"
        ],
        "right_arrow": true,
        "boxed": true
      },
      {
        "key": "wh_main_skill_node_chs_sigvald_battle_08",
        "image_path": "wh_main_character_abilities_rally.png",
        "is_background_skill": false,
        "name": "Rally!",
        "description": " ",
        "levels": [
          {
            "effects": [
              {
                "icon": "general_ability.png",
                "priority": 600,
                "is_positive_value_good": true,
                "description": "Ability: \"Rally!\"",
                "related_abilities": [
                  {
                    "effect": "wh_main_effect_ability_enable_rally",
                    "bonus_value_id": "enable",
                    "unit_ability": {
                      "key": "wh_main_character_abilities_rally",
                      "icon_name": "wh_main_character_abilities_rally",
                      "overpower_option": "",
                      "type": {
                        "key": "wh_type_area_of_augments",
                        "icon_path": "icon_spell_area_of_augments.png",
                        "description": "Augment (Area)"
                      },
                      "is_hidden_in_ui": false,
                      "description": "Rally!",
                      "active_time": 14,
                      "recharge_time": 60,
                      "effect_range": 40,
                      "target_friends": false,
                      "target_enemies": false,
                      "target_ground": false,
                      "target_intercept_range": 0,
                      "target_self": false,
                      "phases": [
                        {
                          "duration": 14,
                          "effect_type": "positive",
                          "max_damaged_entities": -1,
                          "is_hidden_in_ui": false,
                          "stat_effects": [
                            {
                              "value": 16,
                              "stat": "stat_morale",
                              "how": "add",
                              "description": "+16 Leadership",
                              "sort_order": 1,
                              "icon": "icon_stat_morale.png"
                            }
                          ]
                        }
                      ]
                    }
                  }
                ],
                "key": "wh_main_effect_ability_enable_rally",
                "value": 1
              }
            ]
          }
        ],
        "character_skill_key": "wh_main_skill_all_lord_battle_rally",
        "tier": 7,
        "indent": 4,
        "points_on_creation": 0,
        "required_num_parents": 6,
        "visible_in_ui": true,
        "parent_subset_required": [
          "wh_main_skill_node_chs_sigvald_battle_02",
          "wh_main_skill_node_chs_sigvald_battle_03",
          "wh_main_skill_node_chs_sigvald_battle_04",
          "wh_main_skill_node_chs_sigvald_battle_05",
          "wh_main_skill_node_chs_sigvald_battle_06",
          "wh_main_skill_node_chs_sigvald_battle_07"
        ],
        "right_arrow": true
      },
      {
        "key": "wh_main_skill_node_chs_sigvald_battle_09",
        "image_path": "battle_damage.png",
        "is_background_skill": false,
        "name": "Legion of Doom",
        "description": "The legions march forth under the Lord's inscrutable gaze, eager to kill for fear of his wrath.",
        "levels": [
          {
            "effects": [
              {
                "icon": "weapon_damage.png",
                "priority": 108,
                "is_positive_value_good": true,
                "description": "Weapon strength: +12% for Chaos Marauders, Chaos Warriors, Forsaken, Aspiring Champions, and Chosen units (Rank 7 and above)\n\t(Lord's army)",
                "key": "wh2_dlc11_effect_skill_weapon_damage_increase_chs_marauders_aspiring_champions_forsaken_chaos_warriors_chosen_rank7",
                "value": 12
              },
              {
                "icon": "melee.png",
                "priority": 109,
                "is_positive_value_good": true,
                "description": "Melee attack: +5 for Chaos Marauders, Chaos Warriors, Forsaken, Aspiring Champions, and Chosen units (Rank 7 and above)\n\t(Lord's army)",
                "key": "wh2_dlc11_effect_skill_melee_attack_increase_chs_marauders_aspiring_champions_forsaken_chaos_warriors_chosen_rank7",
                "value": 5
              },
              {
                "icon": "resistance_magic.png",
                "priority": 704,
                "is_positive_value_good": true,
                "description": "Magic resistance: 15% for Chaos Marauders, Chaos Warriors, Forsaken, Aspiring Champions, and Chosen units (Rank 7 and above)\n\t(Lord's army)",
                "key": "wh2_dlc11_effect_skill_magic_resist_increase_chs_marauders_aspiring_champions_forsaken_chaos_warriors_chosen_rank7",
                "value": 15
              }
            ]
          }
        ],
        "character_skill_key": "wh2_dlc11_skill_chs_army_buff_legion_of_doom",
        "tier": 8,
        "indent": 4,
        "points_on_creation": 0,
        "required_num_parents": 0,
        "visible_in_ui": true,
        "parent_required": [
          "wh_main_skill_node_chs_sigvald_battle_08"
        ],
        "boxed": true
      },
      {
        "key": "wh_main_skill_node_chs_sigvald_battle_10",
        "image_path": "battle_speed.png",
        "is_background_skill": false,
        "name": "Speed & Malice",
        "description": "The worthiest of Chaos' vanguard are blessed with the most elaborate mutations, which also enable them to run faster for longer.",
        "levels": [
          {
            "effects": [
              {
                "icon": "resistance_missile.png",
                "priority": 55,
                "is_positive_value_good": true,
                "description": "Missile resistance: 15% for Chaos Warhounds, Chaos Chariot, Gorebeast Chariot, Chaos Knights, Dragon Ogres, and Chaos Feral Manticore units (Rank 7 and above)\n\t(Lord's army)",
                "key": "wh2_dlc11_effect_skill_missile_resist_increase_chs_chariots_chaos_knights_dragon_ogres_warhounds_manticore_rank7",
                "value": 15
              },
              {
                "icon": "battle_movement.png",
                "priority": 115,
                "is_positive_value_good": true,
                "description": "Speed: +10% for Chaos Warhounds, Chaos Chariot, Gorebeast Chariot, Chaos Knights, Dragon Ogres, and Chaos Feral Manticore units (Rank 7 and above)\n\t(Lord's army)",
                "key": "wh2_dlc11_effect_skill_speed_increase_chs_chariots_chaos_knights_dragon_ogres_warhounds_manticore_rank7",
                "value": 10
              },
              {
                "icon": "charge.png",
                "priority": 121,
                "is_positive_value_good": true,
                "description": "Charge bonus: +12 for Chaos Warhounds, Chaos Chariot, Gorebeast Chariot, Chaos Knights, Dragon Ogres, and Chaos Feral Manticore units (Rank 7 and above)\n\t(Lord's army)",
                "key": "wh2_dlc11_effect_skill_charge_increase_chs_chariots_chaos_knights_dragon_ogres_warhounds_manticore_rank7",
                "value": 12
              }
            ]
          }
        ],
        "character_skill_key": "wh2_dlc11_skill_chs_army_buff_speed_and_malice",
        "tier": 9,
        "indent": 4,
        "points_on_creation": 0,
        "required_num_parents": 0,
        "visible_in_ui": true,
        "parent_required": [
          "wh_main_skill_node_chs_sigvald_battle_08"
        ],
        "boxed": true
      },
      {
        "key": "wh_main_skill_node_chs_sigvald_battle_11",
        "image_path": "battle_damage.png",
        "is_background_skill": false,
        "name": "Freakish Mutations",
        "description": "Mutations awarded by the Chaos Gods to their followers may look horrific to southerners, but such gifts are prized.",
        "levels": [
          {
            "effects": [
              {
                "icon": "resistance_physical.png",
                "priority": 14,
                "is_positive_value_good": true,
                "description": "Physical resistance: 15% for Chaos Trolls, Chaos Spawn, Chaos Giant, and Dragon Ogre Shaggoth units (Rank 7 and above)\n\t(Lord's army)",
                "key": "wh2_dlc11_effect_skill_physical_resist_increase_chs_trolls_spawn_dragon_ogre_shaggoth_giant_rank7",
                "value": 15
              },
              {
                "icon": "weapon_damage.png",
                "priority": 108,
                "is_positive_value_good": true,
                "description": "Weapon strength: +12% for Chaos Trolls, Chaos Spawn, Chaos Giant, and Dragon Ogre Shaggoth units (Rank 7 and above)\n\t(Lord's army)",
                "key": "wh2_dlc11_effect_skill_weapon_damage_increase_chs_trolls_spawn_dragon_ogre_shaggoth_giant_rank7",
                "value": 12
              },
              {
                "icon": "melee.png",
                "priority": 109,
                "is_positive_value_good": true,
                "description": "Melee attack: +5 for Chaos Trolls, Chaos Spawn, Chaos Giant, and Dragon Ogre Shaggoth units (Rank 7 and above)\n\t(Lord's army)",
                "key": "wh2_dlc11_effect_skill_melee_attack_increase_chs_trolls_spawn_dragon_ogre_shaggoth_giant_rank7",
                "value": 5
              }
            ]
          }
        ],
        "character_skill_key": "wh2_dlc11_skill_chs_army_buff_freakish_mutations",
        "tier": 10,
        "indent": 4,
        "points_on_creation": 0,
        "required_num_parents": 0,
        "visible_in_ui": true,
        "parent_required": [
          "wh_main_skill_node_chs_sigvald_battle_08"
        ],
        "boxed": true
      },
      {
        "key": "wh_main_skill_node_chs_sigvald_battle_12",
        "image_path": "battle_ranged_damage.png",
        "is_background_skill": false,
        "name": "Guided by Tzeentch",
        "description": "Impossible foresight is granted to a few among the ranks of the Ruinous armies, allowing them to land the critical blow upon their foes.",
        "levels": [
          {
            "effects": [
              {
                "icon": "icon_stat_reload_time_force.png",
                "priority": 101,
                "is_positive_value_good": true,
                "description": "Reload time reduction: +10% for Hellcannon, Marauder Horsemen, and Marauder Horsemasters units (Rank 7 and above)\n\t(Lord's army)",
                "key": "wh2_dlc11_effect_skill_reload_increase_chs_hellcannon_marauder_horsemen_rank7",
                "value": 10
              },
              {
                "icon": "ammo.png",
                "priority": 201,
                "is_positive_value_good": true,
                "description": "Ammunition: +15% for Hellcannon, Marauder Horsemen, and Marauder Horsemasters units (Rank 7 and above)\n\t(Lord's army)",
                "key": "wh2_dlc11_effect_skill_ammo_increase_chs_hellcannon_marauder_horsemen_rank7",
                "value": 15
              },
              {
                "icon": "ranged_damage.png",
                "priority": 203,
                "is_positive_value_good": true,
                "description": "Missile strength: +12% for Hellcannon, Marauder Horsemen and Marauder Horsemasters units (Rank 7 and above)\n\t(Lord's army)",
                "key": "wh2_dlc11_effect_skill_missile_damage_increase_chs_hellcannon_marauder_horsemen_rank7",
                "value": 12
              }
            ]
          }
        ],
        "character_skill_key": "wh2_dlc11_skill_chs_army_buff_guided_by_tzeentch",
        "tier": 11,
        "indent": 4,
        "points_on_creation": 0,
        "required_num_parents": 0,
        "visible_in_ui": true,
        "parent_required": [
          "wh_main_skill_node_chs_sigvald_battle_08"
        ],
        "right_arrow": true,
        "boxed": true
      },
      {
        "key": "wh_main_skill_node_chs_sigvald_battle_13",
        "image_path": "wh_main_character_abilities_stand_or_die.png",
        "is_background_skill": false,
        "name": "Stand or Die!",
        "description": " ",
        "levels": [
          {
            "effects": [
              {
                "icon": "general_ability.png",
                "priority": 600,
                "is_positive_value_good": true,
                "description": "Ability: \"Stand or Die!\"",
                "related_abilities": [
                  {
                    "effect": "wh_main_effect_ability_enable_stand_or_die",
                    "bonus_value_id": "enable",
                    "unit_ability": {
                      "key": "wh_main_character_abilities_stand_or_die",
                      "icon_name": "wh_main_character_abilities_stand_or_die",
                      "overpower_option": "",
                      "type": {
                        "key": "wh_type_area_of_augments",
                        "icon_path": "icon_spell_area_of_augments.png",
                        "description": "Augment (Area)"
                      },
                      "is_hidden_in_ui": false,
                      "description": "Stand or Die!",
                      "active_time": 18,
                      "recharge_time": 90,
                      "effect_range": 40,
                      "target_friends": false,
                      "target_enemies": false,
                      "target_ground": false,
                      "target_intercept_range": 0,
                      "target_self": false,
                      "phases": [
                        {
                          "duration": 18,
                          "effect_type": "positive",
                          "max_damaged_entities": -1,
                          "is_hidden_in_ui": false,
                          "stat_effects": [
                            {
                              "value": 24,
                              "stat": "stat_melee_defence",
                              "how": "add",
                              "description": "+24 Melee Defence",
                              "sort_order": 3,
                              "icon": "icon_stat_defence.png"
                            },
                            {
                              "value": 16,
                              "stat": "stat_morale",
                              "how": "add",
                              "description": "+16 Leadership",
                              "sort_order": 1,
                              "icon": "icon_stat_morale.png"
                            }
                          ]
                        }
                      ]
                    }
                  }
                ],
                "key": "wh_main_effect_ability_enable_stand_or_die",
                "value": 1
              },
              {
                "icon": "general_ability.png",
                "priority": 605,
                "is_positive_value_good": true,
                "description": "Replaces: \"Rally!\"",
                "key": "wh_main_effect_ability_disable_rally",
                "value": 1
              }
            ]
          }
        ],
        "character_skill_key": "wh_main_skill_chs_lord_battle_stand_or_die",
        "tier": 12,
        "indent": 4,
        "points_on_creation": 0,
        "required_num_parents": 1,
        "visible_in_ui": true,
        "parent_subset_required": [
          "wh_main_skill_node_chs_sigvald_battle_09",
          "wh_main_skill_node_chs_sigvald_battle_10",
          "wh_main_skill_node_chs_sigvald_battle_11",
          "wh_main_skill_node_chs_sigvald_battle_12"
        ]
      }
    ],
    [
      {
        "key": "wh_main_skill_node_chs_sigvald_campaign_01",
        "image_path": "campaign_movement.png",
        "is_background_skill": false,
        "name": "Route Marcher",
        "description": "Those who know the land and its secrets will travel faster and further than the foes who don't.",
        "levels": [
          {
            "effects": [
              {
                "icon": "campaign_movement.png",
                "priority": 100,
                "is_positive_value_good": true,
                "description": "Campaign movement range: +10%",
                "key": "wh_main_effect_agent_movement_range_mod",
                "value": 10
              }
            ]
          }
        ],
        "character_skill_key": "wh_main_skill_all_lord_campaign_route_marcher",
        "tier": 0,
        "indent": 5,
        "points_on_creation": 0,
        "required_num_parents": 0,
        "visible_in_ui": true,
        "right_arrow": true
      },
      {
        "key": "wh_main_skill_node_chs_sigvald_campaign_02",
        "image_path": "campaign_military_spending.png",
        "is_background_skill": false,
        "name": "Despoilers",
        "description": "To despoil, to corrupt and ruin, to break the mortals and take their gods from them - this is what Chaos wants.",
        "levels": [
          {
            "effects": [
              {
                "icon": "income.png",
                "priority": 101,
                "is_positive_value_good": true,
                "description": "Income from raiding: +3%\n\t(Lord's army)",
                "key": "wh_main_effect_force_all_campaign_raid_income",
                "value": 3
              }
            ]
          },
          {
            "effects": [
              {
                "icon": "income.png",
                "priority": 101,
                "is_positive_value_good": true,
                "description": "Income from raiding: +8%\n\t(Lord's army)",
                "key": "wh_main_effect_force_all_campaign_raid_income",
                "value": 8
              },
              {
                "icon": "income.png",
                "priority": 101,
                "is_positive_value_good": true,
                "description": "Income from razing settlements: +3%",
                "key": "wh_main_effect_force_all_campaign_razing_income",
                "value": 3
              }
            ]
          },
          {
            "effects": [
              {
                "icon": "income.png",
                "priority": 101,
                "is_positive_value_good": true,
                "description": "Income from raiding: +15%\n\t(Lord's army)",
                "key": "wh_main_effect_force_all_campaign_raid_income",
                "value": 15
              },
              {
                "icon": "income.png",
                "priority": 101,
                "is_positive_value_good": true,
                "description": "Income from razing settlements: +8%",
                "key": "wh_main_effect_force_all_campaign_razing_income",
                "value": 8
              }
            ]
          }
        ],
        "character_skill_key": "wh_main_skill_chs_lord_campaign_despoilers",
        "tier": 1,
        "indent": 5,
        "points_on_creation": 0,
        "required_num_parents": 0,
        "visible_in_ui": true,
        "parent_required": [
          "wh_main_skill_node_chs_sigvald_campaign_01"
        ],
        "boxed": true
      },
      {
        "key": "wh_main_skill_node_chs_sigvald_campaign_03",
        "image_path": "campaign_military_spending.png",
        "is_background_skill": false,
        "name": "Serve or Die",
        "description": "\"You will serve me, wretch, or you will die, there is no other option.\"",
        "levels": [
          {
            "effects": [
              {
                "icon": "treasury.png",
                "priority": 106,
                "is_positive_value_good": false,
                "description": "Recruitment cost: -3%\n\t(Lord's army)",
                "key": "wh_main_effect_force_all_campaign_recruitment_cost_all",
                "value": -3
              }
            ]
          },
          {
            "effects": [
              {
                "icon": "treasury.png",
                "priority": 106,
                "is_positive_value_good": false,
                "description": "Recruitment cost: -8%\n\t(Lord's army)",
                "key": "wh_main_effect_force_all_campaign_recruitment_cost_all",
                "value": -8
              }
            ]
          },
          {
            "effects": [
              {
                "icon": "treasury.png",
                "priority": 106,
                "is_positive_value_good": false,
                "description": "Recruitment cost: -15%\n\t(Lord's army)",
                "key": "wh_main_effect_force_all_campaign_recruitment_cost_all",
                "value": -15
              }
            ]
          }
        ],
        "character_skill_key": "wh_main_skill_chs_lord_campaign_serve_or_die",
        "tier": 2,
        "indent": 5,
        "points_on_creation": 0,
        "required_num_parents": 0,
        "visible_in_ui": true,
        "parent_required": [
          "wh_main_skill_node_chs_sigvald_campaign_01"
        ],
        "boxed": true
      },
      {
        "key": "wh_main_skill_node_chs_sigvald_campaign_04",
        "image_path": "campaign_growth.png",
        "is_background_skill": false,
        "name": "Tribes of Chaos",
        "description": "A Lord that was once part of the tribes - one who rode the great Norscan migrations - can summon his kin.",
        "levels": [
          {
            "effects": [
              {
                "icon": "growth.png",
                "priority": 141,
                "is_positive_value_good": true,
                "description": "Horde growth: +1\n\t(Lord's army)",
                "key": "wh_main_effect_hordebuilding_growth_characters",
                "value": 1
              }
            ]
          },
          {
            "effects": [
              {
                "icon": "growth.png",
                "priority": 141,
                "is_positive_value_good": true,
                "description": "Horde growth: +3\n\t(Lord's army)",
                "key": "wh_main_effect_hordebuilding_growth_characters",
                "value": 3
              }
            ]
          },
          {
            "effects": [
              {
                "icon": "growth.png",
                "priority": 141,
                "is_positive_value_good": true,
                "description": "Horde growth: +5\n\t(Lord's army)",
                "key": "wh_main_effect_hordebuilding_growth_characters",
                "value": 5
              }
            ]
          }
        ],
        "character_skill_key": "wh_main_skill_chs_lord_campaign_tribes_of_chaos",
        "tier": 3,
        "indent": 5,
        "points_on_creation": 0,
        "required_num_parents": 0,
        "visible_in_ui": true,
        "parent_required": [
          "wh_main_skill_node_chs_sigvald_campaign_01"
        ],
        "boxed": true
      },
      {
        "key": "wh_main_skill_node_chs_sigvald_campaign_05",
        "image_path": "campaign_siege_attack.png",
        "is_background_skill": false,
        "name": "Ruination",
        "description": "\"This stinking mortal Hold will fall, my masters have foreseen it. Bring them ruin!\"",
        "levels": [
          {
            "effects": [
              {
                "icon": "siege_attack.png",
                "priority": 102,
                "is_positive_value_good": false,
                "description": "Enemy siege holdout time: -1 (minimum 1 turn)",
                "key": "wh_main_effect_force_army_campaign_siege_attack_holdout_time",
                "value": -1
              }
            ]
          },
          {
            "effects": [
              {
                "icon": "disaster.png",
                "priority": 101,
                "is_positive_value_good": true,
                "description": "Attrition suffered by defender: +10% when laying siege\n\t(local region)",
                "key": "wh_main_effect_force_army_campaign_siege_attack_attrition",
                "value": 10
              },
              {
                "icon": "siege_attack.png",
                "priority": 102,
                "is_positive_value_good": false,
                "description": "Enemy siege holdout time: -2 (minimum 1 turn)",
                "key": "wh_main_effect_force_army_campaign_siege_attack_holdout_time",
                "value": -2
              }
            ]
          },
          {
            "effects": [
              {
                "icon": "disaster.png",
                "priority": 101,
                "is_positive_value_good": true,
                "description": "Attrition suffered by defender: +15% when laying siege\n\t(local region)",
                "key": "wh_main_effect_force_army_campaign_siege_attack_attrition",
                "value": 15
              },
              {
                "icon": "siege_attack.png",
                "priority": 102,
                "is_positive_value_good": false,
                "description": "Enemy siege holdout time: -3 (minimum 1 turn)",
                "key": "wh_main_effect_force_army_campaign_siege_attack_holdout_time",
                "value": -3
              }
            ]
          }
        ],
        "character_skill_key": "wh_main_skill_chs_lord_campaign_ruination",
        "tier": 4,
        "indent": 5,
        "points_on_creation": 0,
        "required_num_parents": 0,
        "visible_in_ui": true,
        "parent_required": [
          "wh_main_skill_node_chs_sigvald_campaign_01"
        ],
        "right_arrow": true,
        "boxed": true
      },
      {
        "key": "wh_main_skill_node_chs_sigvald_campaign_06",
        "image_path": "campaign_wound_time.png",
        "is_background_skill": false,
        "name": "Unholy Resilience",
        "description": "This willing servant of the Ruinous Powers has a resilience that is beyond any mortal measure.",
        "levels": [
          {
            "effects": [
              {
                "icon": "replenishment.png",
                "priority": 1,
                "is_positive_value_good": true,
                "description": "Casualty replenishment rate: +30% for Lords\n\t(Lord's army)",
                "key": "wh2_main_effect_replenishment_lords",
                "value": 30
              },
              {
                "icon": "wound_time.png",
                "priority": 101,
                "is_positive_value_good": false,
                "description": "Wound recovery time: -1",
                "key": "wh_main_effect_character_wound_recovery_time_mod",
                "value": -1
              }
            ]
          }
        ],
        "character_skill_key": "wh_main_skill_chs_lord_campaign_unholy_resilience",
        "tier": 5,
        "indent": 5,
        "points_on_creation": 0,
        "required_num_parents": 4,
        "visible_in_ui": true,
        "parent_subset_required": [
          "wh_main_skill_node_chs_sigvald_campaign_02",
          "wh_main_skill_node_chs_sigvald_campaign_03",
          "wh_main_skill_node_chs_sigvald_campaign_04",
          "wh_main_skill_node_chs_sigvald_campaign_05"
        ],
        "right_arrow": true
      },
      {
        "key": "wh_main_skill_node_chs_sigvald_campaign_07",
        "image_path": "campaign_subterfuge.png",
        "is_background_skill": false,
        "name": "Lightning Strike",
        "description": "\"The time to strike is now!\"",
        "levels": [
          {
            "effects": [
              {
                "icon": "subterfuge.png",
                "priority": 10,
                "is_positive_value_good": true,
                "description": "Enables lightning strike battles when reinforcements are present",
                "key": "wh_main_effect_conquest_enable_night_battles",
                "value": 1
              }
            ]
          }
        ],
        "character_skill_key": "wh_main_skill_all_lord_campaign_lightning_strike",
        "tier": 6,
        "indent": 5,
        "points_on_creation": 0,
        "required_num_parents": 0,
        "visible_in_ui": true,
        "parent_required": [
          "wh_main_skill_node_chs_sigvald_campaign_06"
        ],
        "boxed": true
      },
      {
        "key": "wh_main_skill_node_chs_sigvald_campaign_08",
        "image_path": "campaign_disaster.png",
        "is_background_skill": false,
        "name": "Dark Apothecary",
        "description": "The Dark Apothecaries mix their fell unguents, ensuring those that can continue to serve.",
        "levels": [
          {
            "effects": [
              {
                "icon": "disaster.png",
                "priority": 100,
                "is_positive_value_good": false,
                "description": "Attrition: -10% casualties suffered from all attrition\n\t(Lord's army)",
                "key": "wh_main_effect_force_army_campaign_attrition_all_resistance",
                "value": -10
              },
              {
                "icon": "replenishment.png",
                "priority": 101,
                "is_positive_value_good": true,
                "description": "Casualty replenishment rate: +2%\n\t(Lord's army)",
                "key": "wh_main_effect_force_all_campaign_replenishment_rate_horde",
                "value": 2
              }
            ]
          },
          {
            "effects": [
              {
                "icon": "disaster.png",
                "priority": 100,
                "is_positive_value_good": false,
                "description": "Attrition: -20% casualties suffered from all attrition\n\t(Lord's army)",
                "key": "wh_main_effect_force_army_campaign_attrition_all_resistance",
                "value": -20
              },
              {
                "icon": "replenishment.png",
                "priority": 101,
                "is_positive_value_good": true,
                "description": "Casualty replenishment rate: +4%\n\t(Lord's army)",
                "key": "wh_main_effect_force_all_campaign_replenishment_rate_horde",
                "value": 4
              }
            ]
          },
          {
            "effects": [
              {
                "icon": "disaster.png",
                "priority": 100,
                "is_positive_value_good": false,
                "description": "Attrition: -30% casualties suffered from all attrition\n\t(Lord's army)",
                "key": "wh_main_effect_force_army_campaign_attrition_all_resistance",
                "value": -30
              },
              {
                "icon": "replenishment.png",
                "priority": 101,
                "is_positive_value_good": true,
                "description": "Casualty replenishment rate: +6%\n\t(Lord's army)",
                "key": "wh_main_effect_force_all_campaign_replenishment_rate_horde",
                "value": 6
              }
            ]
          }
        ],
        "character_skill_key": "wh_main_skill_chs_lord_campaign_dark_apothecary",
        "tier": 7,
        "indent": 5,
        "points_on_creation": 0,
        "required_num_parents": 0,
        "visible_in_ui": true,
        "parent_required": [
          "wh_main_skill_node_chs_sigvald_campaign_06"
        ],
        "boxed": true
      },
      {
        "key": "wh_main_skill_node_chs_sigvald_campaign_09",
        "image_path": "campaign_army.png",
        "is_background_skill": false,
        "name": "Gathering of Might",
        "description": "The masses flock to the Lord of Chaos - a dread time will soon fall on the weaklings in the south.",
        "levels": [
          {
            "effects": [
              {
                "icon": "army.png",
                "priority": 101,
                "is_positive_value_good": true,
                "description": "Horde recruitment capacity +1",
                "key": "wh_main_effect_force_all_recruitment_points",
                "value": 1
              }
            ]
          },
          {
            "effects": [
              {
                "icon": "army.png",
                "priority": 101,
                "is_positive_value_good": true,
                "description": "Horde recruitment capacity +1",
                "key": "wh_main_effect_force_all_recruitment_points",
                "value": 1
              },
              {
                "icon": "experience.png",
                "priority": 117,
                "is_positive_value_good": true,
                "description": "Recruit rank: +1 for all units",
                "key": "wh_main_effect_force_all_campaign_experience_base_all",
                "value": 1
              }
            ]
          },
          {
            "effects": [
              {
                "icon": "army.png",
                "priority": 101,
                "is_positive_value_good": true,
                "description": "Horde recruitment capacity +1",
                "key": "wh_main_effect_force_all_recruitment_points",
                "value": 1
              },
              {
                "icon": "experience.png",
                "priority": 117,
                "is_positive_value_good": true,
                "description": "Recruit rank: +2 for all units",
                "key": "wh_main_effect_force_all_campaign_experience_base_all",
                "value": 2
              }
            ]
          }
        ],
        "character_skill_key": "wh_main_skill_chs_lord_campaign_gathering_of_might",
        "tier": 8,
        "indent": 5,
        "points_on_creation": 0,
        "required_num_parents": 0,
        "visible_in_ui": true,
        "parent_required": [
          "wh_main_skill_node_chs_sigvald_campaign_06"
        ],
        "boxed": true
      },
      {
        "key": "wh_main_skill_node_chs_sigvald_campaign_10",
        "image_path": "campaign_ambush.png",
        "is_background_skill": false,
        "name": "Premonition",
        "description": "This being must be touched by Tzeentch, seeing things before they happen.",
        "levels": [
          {
            "effects": [
              {
                "icon": "icon_effects_ambush.png",
                "priority": 110,
                "is_positive_value_good": true,
                "description": "Ambush defence chance: +6%\n\t(Lord's army)",
                "key": "wh_main_effect_force_army_campaign_ambush_defence_success_chance",
                "value": 6
              }
            ]
          },
          {
            "effects": [
              {
                "icon": "subterranean.png",
                "priority": 101,
                "is_positive_value_good": true,
                "description": "Chance of intercepting an army using the Underway, beast-paths or Worldroots: +8%",
                "key": "wh_main_effect_general_mod_tunnel_interception_chance",
                "value": 8
              },
              {
                "icon": "icon_effects_ambush.png",
                "priority": 110,
                "is_positive_value_good": true,
                "description": "Ambush defence chance: +16%\n\t(Lord's army)",
                "key": "wh_main_effect_force_army_campaign_ambush_defence_success_chance",
                "value": 16
              }
            ]
          },
          {
            "effects": [
              {
                "icon": "subterranean.png",
                "priority": 101,
                "is_positive_value_good": true,
                "description": "Chance of intercepting an army using the Underway, beast-paths or Worldroots: +15%",
                "key": "wh_main_effect_general_mod_tunnel_interception_chance",
                "value": 15
              },
              {
                "icon": "icon_effects_ambush.png",
                "priority": 110,
                "is_positive_value_good": true,
                "description": "Ambush defence chance: +30%\n\t(Lord's army)",
                "key": "wh_main_effect_force_army_campaign_ambush_defence_success_chance",
                "value": 30
              }
            ]
          }
        ],
        "character_skill_key": "wh_main_skill_all_lord_campaign_premonition",
        "tier": 9,
        "indent": 5,
        "points_on_creation": 0,
        "required_num_parents": 0,
        "visible_in_ui": true,
        "parent_required": [
          "wh_main_skill_node_chs_sigvald_campaign_06"
        ],
        "right_arrow": true,
        "boxed": true
      },
      {
        "key": "wh_main_skill_node_chs_sigvald_campaign_11",
        "image_path": "campaign_chaos_corruption.png",
        "is_background_skill": false,
        "name": "Corruption",
        "description": "With the servants of Chaos comes the corruption - as the landscape twists, this one speeds the transformation.",
        "levels": [
          {
            "effects": [
              {
                "icon": "religion_chaos.png",
                "priority": 104,
                "is_positive_value_good": true,
                "description": "Chaos corruption: +4\n\t(local province)",
                "key": "wh_main_effect_religion_conversion_chaos",
                "value": 4
              }
            ]
          }
        ],
        "character_skill_key": "wh_main_skill_chs_lord_campaign_corruption",
        "tier": 10,
        "indent": 5,
        "points_on_creation": 0,
        "required_num_parents": 4,
        "visible_in_ui": true,
        "parent_subset_required": [
          "wh_main_skill_node_chs_sigvald_campaign_07",
          "wh_main_skill_node_chs_sigvald_campaign_08",
          "wh_main_skill_node_chs_sigvald_campaign_09",
          "wh_main_skill_node_chs_sigvald_campaign_10"
        ]
      }
    ]
  ],
  "key": "chs_sigvald",
  "backgroundSkills": [
    {
      "key": "wh_main_skill_node_chs_sigvald_innate_01",
      "image_path": "trait_chaos.png",
      "is_background_skill": true,
      "name": "Supreme Vanity",
      "description": "\"Surely such sedition should sour and succumb to Sigvald!\"",
      "levels": [
        {
          "effects": [
            {
              "icon": "growth.png",
              "priority": 141,
              "is_positive_value_good": true,
              "description": "Horde growth: +3\n\t(Lord's army)",
              "key": "wh_main_effect_hordebuilding_growth_characters",
              "value": 3
            },
            {
              "icon": "military_spending.png",
              "priority": 502,
              "is_positive_value_good": false,
              "description": "Upkeep: -60% for Chaos Marauder units\n\t(Lord's army)",
              "key": "wh_main_effect_building_upkeep_reduction_chaos_marauders",
              "value": -60
            },
            {
              "icon": "attribute_ignore_forest_penalties.png",
              "priority": 620,
              "is_positive_value_good": true,
              "description": "Attribute: Strider\n\t(Lord's army)",
              "key": "wh_main_effect_unit_enable_attribute_strider",
              "value": 1
            }
          ]
        }
      ],
      "character_skill_node_set_key": "wh_main_skill_node_set_chs_sigvald",
      "character_skill_key": "wh_main_skill_innate_chs_prince_sigvald_the_magnificent",
      "tier": 0,
      "indent": 6,
      "points_on_creation": 1,
      "required_num_parents": 0,
      "visible_in_ui": false
    }
  ],
  "items": [
    {
      "key": "wh_main_skill_node_chs_sigvald_unique_01",
      "image_path": "item_weapon.png",
      "name": "Sliverslash",
      "description": " ",
      "effects": [
        {
          "icon": "melee_character.png",
          "priority": 55,
          "is_positive_value_good": true,
          "description": "Melee attack: +8",
          "value": 8,
          "key": "wh_main_effect_character_stat_mod_melee_attack"
        },
        {
          "icon": "weapon_damage_character.png",
          "priority": 55,
          "is_positive_value_good": true,
          "description": "Weapon strength: +8%",
          "value": 8,
          "key": "wh_main_effect_character_stat_mod_melee_damage"
        },
        {
          "icon": "magical_attacks.png",
          "priority": 61,
          "is_positive_value_good": true,
          "description": "Enables magical attacks",
          "value": 1,
          "key": "wh_main_effect_character_stat_enable_magic_attacks"
        },
        {
          "icon": "religion_chaos.png",
          "priority": 104,
          "is_positive_value_good": true,
          "description": "Chaos corruption: +5",
          "value": 5,
          "key": "wh_main_effect_religion_conversion_chaos"
        },
        {
          "icon": "treasury.png",
          "priority": 106,
          "is_positive_value_good": false,
          "description": "Recruitment cost: -10%",
          "value": -10,
          "key": "wh_main_effect_force_all_campaign_recruitment_cost_all"
        },
        {
          "icon": "income.png",
          "priority": 201,
          "is_positive_value_good": true,
          "description": "Income from post-battle loot: +10%",
          "value": 10,
          "key": "wh_main_effect_force_all_campaign_post_battle_loot_mod"
        }
      ]
    },
    {
      "key": "wh_main_skill_node_chs_sigvald_unique_02",
      "image_path": "item_armour.png",
      "name": "Auric Armour",
      "description": " ",
      "effects": [
        {
          "icon": "armour_character.png",
          "priority": 55,
          "is_positive_value_good": true,
          "description": "Armour: +6",
          "value": 6,
          "key": "wh_main_effect_character_stat_mod_armour"
        },
        {
          "icon": "defence_character.png",
          "priority": 55,
          "is_positive_value_good": true,
          "description": "Melee defence: +6",
          "value": 6,
          "key": "wh_main_effect_character_stat_mod_melee_defence"
        },
        {
          "icon": "resistance_ward_save.png",
          "priority": 55,
          "is_positive_value_good": true,
          "description": "Ward save: 10%",
          "value": 10,
          "key": "wh_main_effect_character_stat_mod_ward_save"
        },
        {
          "icon": "agent.png",
          "priority": 101,
          "is_positive_value_good": false,
          "description": "Enemy Hero action success chance: -10%",
          "value": -10,
          "key": "wh_main_effect_agent_action_success_chance_enemy"
        },
        {
          "icon": "wound_time.png",
          "priority": 101,
          "is_positive_value_good": false,
          "description": "Wound recovery time: -1",
          "value": -1,
          "key": "wh_main_effect_character_wound_recovery_time_mod"
        },
        {
          "icon": "general_ability.png",
          "priority": 600,
          "is_positive_value_good": true,
          "description": "Passive ability: \"Auric Armour\"",
          "related_abilities": [
            {
              "effect": "wh_main_effect_ability_enable_auric_armour",
              "bonus_value_id": "enable",
              "unit_ability": {
                "key": "wh_dlc01_weapon_passive_auric_armour",
                "icon_name": "wh_dlc01_weapon_passive_auric_armour",
                "overpower_option": "",
                "type": {
                  "key": "wh_type_regeneration",
                  "icon_path": "icon_spell_regeneration.png",
                  "description": "Regeneration"
                },
                "is_hidden_in_ui": false,
                "description": "Auric Armour",
                "ui_effects": [
                  {
                    "key": "wh2_dlc15_heal_passive_8",
                    "sort_order": 109,
                    "description": "➕ Restores 8 Hit Points per second"
                  }
                ],
                "effect_range": 0,
                "target_friends": false,
                "target_enemies": false,
                "target_ground": false,
                "target_intercept_range": 0,
                "target_self": false,
                "phases": [
                  {
                    "duration": -1,
                    "effect_type": "positive",
                    "hp_change_frequency": 0.5,
                    "heal_amount": 4,
                    "is_hidden_in_ui": false
                  }
                ]
              }
            }
          ],
          "value": 1,
          "key": "wh_main_effect_ability_enable_auric_armour"
        }
      ]
    }
  ]
}
